{
  "schemaVersion": 2,
  "id": "accessible-css-preferences-regression",
  "courseId": "responsive-web-design",
  "title": "Accessible CSS under Real User Preferences",
  "description": "Preserve complete tasks under zoom and reflow, choose hidden-state behavior accurately, protect focus, adapt to user preferences, create generous targets, and repeat accessibility regression checks after every visual change.",
  "order": 18,
  "objectives": [
    "Complete critical workflows at high zoom and narrow effective widths without lost content or controls.",
    "Match hidden techniques to visual, layout, focus, hit-test, and accessibility-tree intent.",
    "Protect focus and preserve meaningful feedback under reduced motion, contrast, dark scheme, and forced colors.",
    "Provide generous multi-input targets and attach repeated access evidence to every cumulative build."
  ],
  "competencyIds": [
    "css-zoom-reflow",
    "css-visible-hidden-content",
    "css-focus-visibility",
    "css-user-preferences",
    "css-touch-targets",
    "css-accessibility-regression"
  ],
  "prerequisites": [
    "readable-responsive-typography"
  ],
  "activityIds": [
    "zoom-reflow-stress-lab",
    "hidden-state-contract-lab",
    "focus-visibility-regression-lab",
    "user-preference-adaptation-lab",
    "target-spacing-pointer-lab",
    "css-access-regression-matrix",
    "mapped-lecture-best-practices-for-accessibility-and-css",
    "mapped-workshop-accessibility-quiz",
    "mapped-lab-tribute-page",
    "mapped-review-css-accessibility",
    "mapped-quiz-css-accessibility"
  ]
}
