{
  "schemaVersion": 1,
  "courseId": "responsive-web-design",
  "scopeId": "html-foundations",
  "status": "researching",
  "reviewedAt": "2026-07-15",
  "sourceIds": [
    "rwd-whatwg-html",
    "rwd-wcag-two-two",
    "rwd-mdn-curriculum",
    "rwd-webdev-html",
    "rwd-mdn-browser-loading",
    "rwd-wai-tutorials",
    "rwd-aria-apg",
    "rwd-fcc-v9",
    "rwd-fcc-opening-inspection"
  ],
  "moduleIds": [
    "html-first-page",
    "html-documents-and-paths",
    "html-images-and-media",
    "html-text-and-semantics",
    "html-forms",
    "html-tables",
    "html-accessibility-and-debugging",
    "html-independent-project"
  ],
  "requiredStages": [
    "introduce",
    "model",
    "guided",
    "faded",
    "debug",
    "retrieve",
    "assess",
    "transfer"
  ],
  "concepts": [
    {
      "id": "html-workspace-feedback-loop",
      "title": "Source, preview, and saved artifact",
      "objective": "Edit one bounded source file, connect the changed characters to parsed preview output, save it, and resume the exact artifact state.",
      "order": 1,
      "moduleId": "html-first-page",
      "prerequisiteIds": [],
      "sourceAnchors": [
        {
          "sourceId": "rwd-fcc-opening-inspection",
          "locator": "workshop-curriculum-outline steps 1-3",
          "claim": "Current benchmark introduces the editor and connects an immediate source edit to preview output."
        }
      ],
      "misconceptions": [
        "The preview is the source file, so a visible result proves the saved source is correct."
      ],
      "evidenceRequirements": [
        "Changed text must appear in the preview and remain after a reload.",
        "Learner must identify source, parsed output, saved draft, and last passing checkpoint separately."
      ],
      "stages": [
        "introduce",
        "model",
        "guided",
        "faded",
        "debug",
        "retrieve",
        "assess",
        "transfer"
      ],
      "retainedInModuleIds": [
        "html-documents-and-paths",
        "html-independent-project"
      ],
      "currentState": "researched-not-authored"
    },
    {
      "id": "html-purpose-structure",
      "title": "HTML purpose and boundary",
      "objective": "Explain and demonstrate that HTML describes document content and meaning while CSS handles presentation and JavaScript handles dynamic behavior.",
      "order": 2,
      "moduleId": "html-first-page",
      "prerequisiteIds": [
        "html-workspace-feedback-loop"
      ],
      "sourceAnchors": [
        {
          "sourceId": "rwd-mdn-curriculum",
          "locator": "Web standards 1.2 and Semantic HTML overview",
          "claim": "MDN separates HTML structure and semantics from CSS presentation and JavaScript behavior."
        }
      ],
      "misconceptions": [
        "HTML is a programming language whose element names directly specify visual styling."
      ],
      "evidenceRequirements": [
        "Learner must classify changed requirements as content, semantics, presentation, or behavior.",
        "Artifact must remain understandable before author CSS or JavaScript is added."
      ],
      "stages": [
        "introduce",
        "model",
        "guided",
        "faded",
        "debug",
        "retrieve",
        "assess",
        "transfer"
      ],
      "retainedInModuleIds": [
        "html-independent-project"
      ],
      "currentState": "researched-not-authored"
    },
    {
      "id": "html-element-anatomy",
      "title": "Element anatomy",
      "objective": "Identify and author element, start tag, tag name, content, and end tag without confusing any part for the complete element.",
      "order": 3,
      "moduleId": "html-first-page",
      "prerequisiteIds": [
        "html-purpose-structure"
      ],
      "sourceAnchors": [
        {
          "sourceId": "rwd-whatwg-html",
          "locator": "HTML syntax 13.1.2",
          "claim": "The standard defines tags as markup delimiters and gives normative start-tag and end-tag syntax."
        },
        {
          "sourceId": "rwd-webdev-html",
          "locator": "Overview: Elements",
          "claim": "Learn HTML distinguishes opening tag, closing tag, content, and complete element."
        }
      ],
      "misconceptions": [
        "An opening tag by itself is the complete HTML element."
      ],
      "evidenceRequirements": [
        "Learner must label anatomy in valid and malformed examples.",
        "Learner must author an unfamiliar normal element from a content requirement without copied source."
      ],
      "stages": [
        "introduce",
        "model",
        "guided",
        "faded",
        "debug",
        "retrieve",
        "assess",
        "transfer"
      ],
      "retainedInModuleIds": [
        "html-independent-project"
      ],
      "currentState": "researched-not-authored"
    },
    {
      "id": "html-tag-element-distinction",
      "title": "Tags, elements, and nodes",
      "objective": "Distinguish source tags from DOM elements and text nodes, then explain why source serialization and parsed structure can differ.",
      "order": 4,
      "moduleId": "html-first-page",
      "prerequisiteIds": [
        "html-element-anatomy"
      ],
      "sourceAnchors": [
        {
          "sourceId": "rwd-webdev-html",
          "locator": "Overview: document tree and elements",
          "claim": "HTML documents are node trees containing elements and text nodes rather than a flat sequence of visible tags."
        }
      ],
      "misconceptions": [
        "Every tag becomes a separate visible DOM node, including closing tags."
      ],
      "evidenceRequirements": [
        "Learner must match source ranges to resulting element and text nodes.",
        "Changed-case inspection must explain one source-to-DOM difference without relying on appearance."
      ],
      "stages": [
        "introduce",
        "model",
        "guided",
        "faded",
        "debug",
        "retrieve",
        "assess",
        "transfer"
      ],
      "retainedInModuleIds": [
        "html-independent-project"
      ],
      "currentState": "researched-not-authored"
    },
    {
      "id": "html-text-whitespace",
      "title": "Text nodes and whitespace",
      "objective": "Predict how ordinary text, spaces, line breaks, and reserved characters become text nodes and rendered inline content.",
      "order": 5,
      "moduleId": "html-first-page",
      "prerequisiteIds": [
        "html-element-anatomy"
      ],
      "sourceAnchors": [
        {
          "sourceId": "rwd-whatwg-html",
          "locator": "HTML syntax text and character references",
          "claim": "Normal elements may contain text and character references subject to syntax and content-model restrictions."
        }
      ],
      "misconceptions": [
        "Indentation and repeated source spaces always render exactly as typed."
      ],
      "evidenceRequirements": [
        "Learner must predict DOM text and visible spacing for changed indentation and text.",
        "Artifact must preserve intended words while using elements rather than spaces for document structure."
      ],
      "stages": [
        "introduce",
        "model",
        "guided",
        "faded",
        "debug",
        "retrieve",
        "assess",
        "transfer"
      ],
      "retainedInModuleIds": [
        "html-independent-project"
      ],
      "currentState": "researched-not-authored"
    },
    {
      "id": "html-nesting-tree",
      "title": "Nesting and tree relationships",
      "objective": "Author and inspect parent, child, descendant, ancestor, and sibling relationships using valid nesting rather than indentation alone.",
      "order": 6,
      "moduleId": "html-first-page",
      "prerequisiteIds": [
        "html-element-anatomy",
        "html-text-whitespace"
      ],
      "sourceAnchors": [
        {
          "sourceId": "rwd-mdn-curriculum",
          "locator": "Semantic HTML 2.2 good document structure",
          "claim": "MDN requires correct nesting because browser repair may produce a different structure than the author intended."
        }
      ],
      "misconceptions": [
        "Indentation creates parent-child relationships even when tags close in another order."
      ],
      "evidenceRequirements": [
        "Learner must draw and verify the tree produced by nested source.",
        "Malformed close-order case must be repaired from DOM evidence and then survive a changed sibling insertion."
      ],
      "stages": [
        "introduce",
        "model",
        "guided",
        "faded",
        "debug",
        "retrieve",
        "assess",
        "transfer"
      ],
      "retainedInModuleIds": [
        "html-independent-project"
      ],
      "currentState": "researched-not-authored"
    },
    {
      "id": "html-content-models",
      "title": "Allowed content relationships",
      "objective": "Use element content models and contextual author requirements to decide whether a parent-child relationship is conforming and meaningful.",
      "order": 7,
      "moduleId": "html-first-page",
      "prerequisiteIds": [
        "html-nesting-tree"
      ],
      "sourceAnchors": [
        {
          "sourceId": "rwd-whatwg-html",
          "locator": "HTML elements and content models",
          "claim": "Elements impose content categories, models, and contextual author restrictions beyond basic tag syntax."
        }
      ],
      "misconceptions": [
        "Any element can contain any other element when the browser displays it."
      ],
      "evidenceRequirements": [
        "Learner must reject a visually plausible but invalid content relationship and cite the controlling model.",
        "Independent build must pass parsed-relationship checks rather than source token checks."
      ],
      "stages": [
        "introduce",
        "model",
        "guided",
        "faded",
        "debug",
        "retrieve",
        "assess",
        "transfer"
      ],
      "retainedInModuleIds": [
        "html-independent-project"
      ],
      "currentState": "researched-not-authored"
    },
    {
      "id": "html-void-elements",
      "title": "Void elements",
      "objective": "Recognize and author void elements without invented end tags or XHTML self-closing assumptions, then explain how their attributes provide behavior.",
      "order": 8,
      "moduleId": "html-first-page",
      "prerequisiteIds": [
        "html-element-anatomy"
      ],
      "sourceAnchors": [
        {
          "sourceId": "rwd-whatwg-html",
          "locator": "HTML syntax 13.1.2 void elements",
          "claim": "Void elements have no end tag; a trailing slash does not make an HTML void element self-closing."
        }
      ],
      "misconceptions": [
        "A trailing slash closes any HTML element and prevents later text from becoming its content."
      ],
      "evidenceRequirements": [
        "Learner must distinguish normal, void, and foreign-element syntax in changed examples.",
        "Malformed void-element source must be diagnosed from parsed attributes and following content."
      ],
      "stages": [
        "introduce",
        "model",
        "guided",
        "faded",
        "debug",
        "retrieve",
        "assess",
        "transfer"
      ],
      "retainedInModuleIds": [
        "html-independent-project"
      ],
      "currentState": "researched-not-authored"
    },
    {
      "id": "html-attribute-syntax",
      "title": "Attribute names and values",
      "objective": "Place attributes inside a start tag and author separated names and values using unambiguous quoting and specification-defined names.",
      "order": 9,
      "moduleId": "html-first-page",
      "prerequisiteIds": [
        "html-element-anatomy"
      ],
      "sourceAnchors": [
        {
          "sourceId": "rwd-whatwg-html",
          "locator": "HTML syntax 13.1.2.3 attributes",
          "claim": "The standard defines attribute placement, names, values, separators, and four serialization forms."
        }
      ],
      "misconceptions": [
        "Attributes belong after an element or inside its closing tag because they describe the complete element."
      ],
      "evidenceRequirements": [
        "Learner must parse name, separator, quote, value, and start-tag boundaries in malformed source.",
        "Changed-case build must apply a valid element-specific attribute and verify its parsed value and behavior."
      ],
      "stages": [
        "introduce",
        "model",
        "guided",
        "faded",
        "debug",
        "retrieve",
        "assess",
        "transfer"
      ],
      "retainedInModuleIds": [
        "html-independent-project"
      ],
      "currentState": "researched-not-authored"
    },
    {
      "id": "html-attribute-value-types",
      "title": "Boolean, enumerated, and text attributes",
      "objective": "Distinguish boolean presence, enumerated keywords, token lists, IDs, URLs, and free text so values follow each attribute contract.",
      "order": 10,
      "moduleId": "html-first-page",
      "prerequisiteIds": [
        "html-attribute-syntax"
      ],
      "sourceAnchors": [
        {
          "sourceId": "rwd-whatwg-html",
          "locator": "Common microsyntaxes and element attribute definitions",
          "claim": "Attribute meaning depends on its specification-defined value type rather than one universal string rule."
        }
      ],
      "misconceptions": [
        "Writing a boolean attribute as false disables it because the word false becomes a false value."
      ],
      "evidenceRequirements": [
        "Learner must predict behavior for present, absent, invalid, and changed attribute values.",
        "Artifact must use boolean and enumerated attributes without relying on string truthiness assumptions."
      ],
      "stages": [
        "introduce",
        "model",
        "guided",
        "faded",
        "debug",
        "retrieve",
        "assess",
        "transfer"
      ],
      "retainedInModuleIds": [
        "html-independent-project"
      ],
      "currentState": "researched-not-authored"
    },
    {
      "id": "html-comments-character-references",
      "title": "Comments and character references",
      "objective": "Use comments for bounded author notes and character references where literal syntax would be ambiguous, without using either as page structure.",
      "order": 11,
      "moduleId": "html-first-page",
      "prerequisiteIds": [
        "html-element-anatomy"
      ],
      "sourceAnchors": [
        {
          "sourceId": "rwd-whatwg-html",
          "locator": "HTML syntax comments and character references",
          "claim": "HTML defines separate comment syntax and character-reference parsing rules."
        }
      ],
      "misconceptions": [
        "Commented secrets are safe because users cannot see comments in the rendered page."
      ],
      "evidenceRequirements": [
        "Learner must render reserved characters without accidentally creating markup.",
        "Inspection must locate a comment in source and DOM and explain why sensitive data never belongs there."
      ],
      "stages": [
        "introduce",
        "model",
        "guided",
        "faded",
        "debug",
        "retrieve",
        "assess",
        "transfer"
      ],
      "retainedInModuleIds": [
        "html-independent-project"
      ],
      "currentState": "researched-not-authored"
    },
    {
      "id": "html-parser-recovery",
      "title": "Browser parsing and recovery",
      "objective": "Compare authored source with the DOM produced by browser error recovery, then repair the cause and verify a conforming stable tree.",
      "order": 12,
      "moduleId": "html-first-page",
      "prerequisiteIds": [
        "html-nesting-tree",
        "html-content-models"
      ],
      "sourceAnchors": [
        {
          "sourceId": "rwd-whatwg-html",
          "locator": "Parsing HTML documents",
          "claim": "Browsers construct a DOM through defined parsing and error-recovery behavior rather than displaying source literally."
        }
      ],
      "misconceptions": [
        "If malformed HTML looks acceptable in one browser, the source is valid and interoperable."
      ],
      "evidenceRequirements": [
        "Learner must predict and inspect recovery for a missing or misplaced tag.",
        "Repair must pass source conformance, expected DOM structure, and a changed insertion case."
      ],
      "stages": [
        "introduce",
        "model",
        "guided",
        "faded",
        "debug",
        "retrieve",
        "assess",
        "transfer"
      ],
      "retainedInModuleIds": [
        "html-independent-project"
      ],
      "currentState": "researched-not-authored"
    },
    {
      "id": "html-doctype-rendering-mode",
      "title": "Doctype and rendering mode",
      "objective": "Place the HTML doctype first and explain its current rendering-mode purpose without treating it as an HTML element or version declaration.",
      "order": 13,
      "moduleId": "html-documents-and-paths",
      "prerequisiteIds": [
        "html-parser-recovery"
      ],
      "sourceAnchors": [
        {
          "sourceId": "rwd-whatwg-html",
          "locator": "HTML syntax 13.1.1 DOCTYPE",
          "claim": "A doctype is required legacy preamble that avoids incompatible rendering modes."
        },
        {
          "sourceId": "rwd-mdn-curriculum",
          "locator": "Semantic HTML 2.1 basic syntax",
          "claim": "MDN requires understanding both doctype use and its historical status."
        }
      ],
      "misconceptions": [
        "The doctype is the root HTML element and tells the browser which modern HTML version to download."
      ],
      "evidenceRequirements": [
        "Learner must distinguish doctype node, document element, and rendered content.",
        "Changed document without a correct doctype must expose mode evidence and be repaired."
      ],
      "stages": [
        "introduce",
        "model",
        "guided",
        "faded",
        "debug",
        "retrieve",
        "assess",
        "transfer"
      ],
      "retainedInModuleIds": [
        "html-independent-project"
      ],
      "currentState": "researched-not-authored"
    },
    {
      "id": "html-document-root-head-body",
      "title": "Complete document structure",
      "objective": "Author a complete document with doctype, html root, metadata head, titled document, and content body from an empty file.",
      "order": 14,
      "moduleId": "html-documents-and-paths",
      "prerequisiteIds": [
        "html-doctype-rendering-mode",
        "html-nesting-tree"
      ],
      "sourceAnchors": [
        {
          "sourceId": "rwd-whatwg-html",
          "locator": "HTML syntax writing documents",
          "claim": "A conforming serialized document has a doctype and html document element containing head and body structure."
        }
      ],
      "misconceptions": [
        "A body fragment that renders is equivalent to a complete portable HTML document."
      ],
      "evidenceRequirements": [
        "Learner must build the complete envelope without receiving hidden scaffold source.",
        "Source, DOM, title-bar, and validation evidence must distinguish head metadata from body content."
      ],
      "stages": [
        "introduce",
        "model",
        "guided",
        "faded",
        "debug",
        "retrieve",
        "assess",
        "transfer"
      ],
      "retainedInModuleIds": [
        "html-independent-project"
      ],
      "currentState": "researched-not-authored"
    },
    {
      "id": "html-document-language",
      "title": "Document language",
      "objective": "Declare the primary human language and identify bounded language changes so pronunciation and language processing have programmatic evidence.",
      "order": 15,
      "moduleId": "html-documents-and-paths",
      "prerequisiteIds": [
        "html-document-root-head-body",
        "html-attribute-syntax"
      ],
      "sourceAnchors": [
        {
          "sourceId": "rwd-mdn-curriculum",
          "locator": "Semantic HTML 2.1 language outcome",
          "claim": "MDN requires setting document language on the opening html element."
        },
        {
          "sourceId": "rwd-wcag-two-two",
          "locator": "Success Criteria 3.1.1 and 3.1.2",
          "claim": "Page language and language changes need programmatic determination."
        }
      ],
      "misconceptions": [
        "The lang attribute translates visible text into the chosen language."
      ],
      "evidenceRequirements": [
        "Learner must select valid language tags for page and changed inline-language content.",
        "DOM and accessibility evidence must expose primary and changed language scopes."
      ],
      "stages": [
        "introduce",
        "model",
        "guided",
        "faded",
        "debug",
        "retrieve",
        "assess",
        "transfer"
      ],
      "retainedInModuleIds": [
        "html-independent-project"
      ],
      "currentState": "researched-not-authored"
    },
    {
      "id": "html-character-encoding",
      "title": "Character encoding declaration",
      "objective": "Declare UTF-8 early in the head and diagnose text corruption as a bytes-to-characters interpretation problem.",
      "order": 16,
      "moduleId": "html-documents-and-paths",
      "prerequisiteIds": [
        "html-document-root-head-body",
        "html-attribute-syntax"
      ],
      "sourceAnchors": [
        {
          "sourceId": "rwd-whatwg-html",
          "locator": "Character encoding declarations",
          "claim": "HTML constrains encoding declarations and their serialization position."
        }
      ],
      "misconceptions": [
        "UTF-8 is a font that visually supports more symbols."
      ],
      "evidenceRequirements": [
        "Learner must explain bytes, encoding declaration, characters, and font as separate layers.",
        "Changed non-ASCII content must survive save, reload, parse, and copy evidence."
      ],
      "stages": [
        "introduce",
        "model",
        "guided",
        "faded",
        "debug",
        "retrieve",
        "assess",
        "transfer"
      ],
      "retainedInModuleIds": [
        "html-independent-project"
      ],
      "currentState": "researched-not-authored"
    },
    {
      "id": "html-title-metadata",
      "title": "Document title and bounded metadata",
      "objective": "Write a unique useful document title and only metadata whose consumer and purpose can be named and verified.",
      "order": 17,
      "moduleId": "html-documents-and-paths",
      "prerequisiteIds": [
        "html-document-root-head-body"
      ],
      "sourceAnchors": [
        {
          "sourceId": "rwd-mdn-curriculum",
          "locator": "Semantic HTML 2.1 head outcomes",
          "claim": "MDN includes title, search metadata, icons, stylesheets, and script links in head knowledge."
        }
      ],
      "misconceptions": [
        "The title element creates the largest visible heading in the page body."
      ],
      "evidenceRequirements": [
        "Learner must verify document title separately from visible heading text.",
        "Changed multi-page case must produce distinct meaningful titles without keyword stuffing."
      ],
      "stages": [
        "introduce",
        "model",
        "guided",
        "faded",
        "debug",
        "retrieve",
        "assess",
        "transfer"
      ],
      "retainedInModuleIds": [
        "html-independent-project"
      ],
      "currentState": "researched-not-authored"
    },
    {
      "id": "html-discovery-metadata",
      "title": "Search and sharing discovery metadata",
      "objective": "Provide accurate descriptions, canonical identity, icons, and bounded sharing metadata whose consumers, limitations, and visible-content relationship can be verified.",
      "order": 18,
      "moduleId": "html-documents-and-paths",
      "prerequisiteIds": [
        "html-title-metadata",
        "html-document-language"
      ],
      "sourceAnchors": [
        {
          "sourceId": "rwd-webdev-html",
          "locator": "Metadata and document head coverage",
          "claim": "Document metadata describes the page to browsers, search systems, sharing tools, and other consumers without replacing visible content."
        }
      ],
      "misconceptions": [
        "Metadata keywords can guarantee ranking and may describe content that the visible page does not provide."
      ],
      "evidenceRequirements": [
        "Changed multi-page cases must expose unique truthful title, description, canonical, icon, and sharing evidence without duplicated identity.",
        "Learner must name each metadata consumer, verify inspectable output where possible, and state what the metadata cannot guarantee."
      ],
      "stages": [
        "introduce",
        "model",
        "guided",
        "faded",
        "debug",
        "retrieve",
        "assess",
        "transfer"
      ],
      "retainedInModuleIds": [
        "html-independent-project"
      ],
      "currentState": "researched-not-authored"
    },
    {
      "id": "html-viewport-metadata",
      "title": "Viewport configuration",
      "objective": "Configure the layout viewport for responsive design without restricting zoom or treating metadata as a substitute for resilient CSS.",
      "order": 19,
      "moduleId": "html-documents-and-paths",
      "prerequisiteIds": [
        "html-document-root-head-body",
        "html-attribute-syntax"
      ],
      "sourceAnchors": [
        {
          "sourceId": "rwd-wcag-two-two",
          "locator": "Success Criteria 1.4.4 and 1.4.10",
          "claim": "Text resizing and reflow must remain available across viewport configuration."
        }
      ],
      "misconceptions": [
        "Setting width=device-width automatically makes fixed-width content responsive."
      ],
      "evidenceRequirements": [
        "Learner must compare layout viewport evidence before and after safe metadata.",
        "Changed fixed-width page must still fail until CSS constraints are repaired, proving metadata is not the layout solution."
      ],
      "stages": [
        "introduce",
        "model",
        "guided",
        "faded",
        "debug",
        "retrieve",
        "assess",
        "transfer"
      ],
      "retainedInModuleIds": [
        "html-independent-project"
      ],
      "currentState": "researched-not-authored"
    },
    {
      "id": "html-files-paths-urls",
      "title": "Files, paths, and URL references",
      "objective": "Organize a portable project and resolve relative, root-relative, absolute, and fragment references from the correct base URL.",
      "order": 20,
      "moduleId": "html-documents-and-paths",
      "prerequisiteIds": [
        "html-workspace-feedback-loop"
      ],
      "sourceAnchors": [
        {
          "sourceId": "rwd-mdn-curriculum",
          "locator": "Semantic HTML 2.5 links",
          "claim": "MDN requires absolute and relative paths plus detailed slash, dot, and double-dot syntax."
        }
      ],
      "misconceptions": [
        "A relative path is relative to the project folder regardless of the current document location."
      ],
      "evidenceRequirements": [
        "Moved-folder and nested-document cases must resolve expected resources without machine-specific paths.",
        "Learner must diagnose case, extension, base, path-segment, and URL-encoding failures from network evidence."
      ],
      "stages": [
        "introduce",
        "model",
        "guided",
        "faded",
        "debug",
        "retrieve",
        "assess",
        "transfer"
      ],
      "retainedInModuleIds": [
        "html-images-and-media",
        "html-independent-project"
      ],
      "currentState": "researched-not-authored"
    },
    {
      "id": "html-browser-request-parse-render",
      "title": "Browser request, parse, and render evidence",
      "objective": "Trace navigation through URL resolution, requests, responses, resource discovery, HTML parsing, DOM construction, CSS matching, layout, paint, and interactive output at a beginner-appropriate level.",
      "order": 21,
      "moduleId": "html-documents-and-paths",
      "prerequisiteIds": [
        "html-files-paths-urls",
        "html-document-root-head-body",
        "html-parser-recovery"
      ],
      "sourceAnchors": [
        {
          "sourceId": "rwd-mdn-browser-loading",
          "locator": "Requests, responses, HTML handling, CSS handling, and rendering",
          "claim": "Browsers request multiple resources, parse HTML into a DOM, parse and match CSS, then assemble rendered output."
        }
      ],
      "misconceptions": [
        "Opening one HTML file makes the browser read every project file automatically without references or requests."
      ],
      "evidenceRequirements": [
        "Learner must connect changed source, requested resources, response failures, DOM nodes, computed styles, and rendered output without collapsing them into one layer.",
        "A missing-resource case must be diagnosed at URL, request, response, parse, match, or render stage using the evidence surface that can prove it."
      ],
      "stages": [
        "introduce",
        "model",
        "guided",
        "faded",
        "debug",
        "retrieve",
        "assess",
        "transfer"
      ],
      "retainedInModuleIds": [
        "html-images-and-media",
        "html-accessibility-and-debugging",
        "html-independent-project"
      ],
      "currentState": "researched-not-authored"
    },
    {
      "id": "html-authority-research-verification",
      "title": "Technical authority and claim verification",
      "objective": "Turn an HTML or browser question into a bounded claim, locate current specification or official documentation evidence, record version and context, test behavior where appropriate, and preserve uncertainty.",
      "order": 22,
      "moduleId": "html-documents-and-paths",
      "prerequisiteIds": [
        "html-browser-request-parse-render"
      ],
      "sourceAnchors": [
        {
          "sourceId": "rwd-mdn-curriculum",
          "locator": "Research technical information and web standards outcomes",
          "claim": "Professional web work requires finding authoritative technical information and separating standards from examples, compatibility observations, and unsupported claims."
        }
      ],
      "misconceptions": [
        "The first search result or generated answer is authoritative when its code appears to work in one browser."
      ],
      "evidenceRequirements": [
        "Learner must produce a claim-evidence-limit-test record for a changed HTML question using a current authority rather than a copied answer.",
        "Conflicting or outdated evidence must be resolved by version, normative status, browser observation, and an explicit remaining-uncertainty statement."
      ],
      "stages": [
        "introduce",
        "model",
        "guided",
        "faded",
        "debug",
        "retrieve",
        "assess",
        "transfer"
      ],
      "retainedInModuleIds": [
        "html-accessibility-and-debugging",
        "html-independent-project"
      ],
      "currentState": "researched-not-authored"
    },
    {
      "id": "html-links-destinations",
      "title": "Links and destinations",
      "objective": "Create anchors whose href values resolve to intended web, file, email, telephone, and same-document destinations with safe behavior.",
      "order": 23,
      "moduleId": "html-documents-and-paths",
      "prerequisiteIds": [
        "html-files-paths-urls",
        "html-attribute-syntax"
      ],
      "sourceAnchors": [
        {
          "sourceId": "rwd-mdn-curriculum",
          "locator": "Semantic HTML 2.5 links",
          "claim": "Links are fundamental web navigation and require href, path, state, and link-text understanding."
        }
      ],
      "misconceptions": [
        "An anchor without href remains an equivalent keyboard-operable hyperlink."
      ],
      "evidenceRequirements": [
        "All changed destinations must resolve and expose correct scheme, path, query, and fragment evidence.",
        "Keyboard and accessibility inspection must identify each functional link and its destination purpose."
      ],
      "stages": [
        "introduce",
        "model",
        "guided",
        "faded",
        "debug",
        "retrieve",
        "assess",
        "transfer"
      ],
      "retainedInModuleIds": [
        "html-independent-project"
      ],
      "currentState": "researched-not-authored"
    },
    {
      "id": "html-link-purpose-fragments",
      "title": "Link purpose and fragment targets",
      "objective": "Write destination-specific link text and stable unique fragment targets that remain understandable outside surrounding prose.",
      "order": 24,
      "moduleId": "html-documents-and-paths",
      "prerequisiteIds": [
        "html-links-destinations",
        "html-attribute-syntax"
      ],
      "sourceAnchors": [
        {
          "sourceId": "rwd-wcag-two-two",
          "locator": "Success Criteria 2.4.4 and 4.1.1",
          "claim": "Link purpose needs context and identifiers must not create ambiguous relationships."
        }
      ],
      "misconceptions": [
        "Repeated click-here links are accessible because each appears beside a descriptive paragraph."
      ],
      "evidenceRequirements": [
        "Link-list inspection must distinguish destinations without nearby prose.",
        "Changed long-page case must navigate to unique named targets without obscuring focus or heading context."
      ],
      "stages": [
        "introduce",
        "model",
        "guided",
        "faded",
        "debug",
        "retrieve",
        "assess",
        "transfer"
      ],
      "retainedInModuleIds": [
        "html-independent-project"
      ],
      "currentState": "researched-not-authored"
    },
    {
      "id": "html-images-purpose-alt",
      "title": "Image purpose and text alternatives",
      "objective": "Classify informative, functional, decorative, complex, and text images, then provide the appropriate text alternative or exclusion.",
      "order": 25,
      "moduleId": "html-images-and-media",
      "prerequisiteIds": [
        "html-files-paths-urls",
        "html-attribute-syntax",
        "html-content-models"
      ],
      "sourceAnchors": [
        {
          "sourceId": "rwd-wai-tutorials",
          "locator": "Images tutorial decision tree",
          "claim": "Alternative treatment depends on image purpose and surrounding content rather than appearance alone."
        }
      ],
      "misconceptions": [
        "Every image needs a detailed literal description in its alt attribute."
      ],
      "evidenceRequirements": [
        "Learner must justify alternative treatment for changed image purposes.",
        "Missing-image and accessibility-tree checks must preserve equivalent task information without redundant announcements."
      ],
      "stages": [
        "introduce",
        "model",
        "guided",
        "faded",
        "debug",
        "retrieve",
        "assess",
        "transfer"
      ],
      "retainedInModuleIds": [
        "html-independent-project"
      ],
      "currentState": "researched-not-authored"
    },
    {
      "id": "html-image-dimensions-loading",
      "title": "Image dimensions and loading behavior",
      "objective": "Provide intrinsic dimensions, appropriate loading behavior, safe sources, and performance evidence without distorting content.",
      "order": 26,
      "moduleId": "html-images-and-media",
      "prerequisiteIds": [
        "html-images-purpose-alt",
        "html-attribute-value-types"
      ],
      "sourceAnchors": [
        {
          "sourceId": "rwd-mdn-curriculum",
          "locator": "Semantic HTML 2.6 media",
          "claim": "MDN includes image dimensions to reduce disruptive layout movement and media optimization."
        }
      ],
      "misconceptions": [
        "Width and height attributes force an image to keep that exact visual size at every viewport."
      ],
      "evidenceRequirements": [
        "Changed aspect-ratio and missing-resource cases must preserve a stable non-distorted layout.",
        "Learner must separate intrinsic dimensions, rendered CSS dimensions, file bytes, and loading priority evidence."
      ],
      "stages": [
        "introduce",
        "model",
        "guided",
        "faded",
        "debug",
        "retrieve",
        "assess",
        "transfer"
      ],
      "retainedInModuleIds": [
        "html-independent-project"
      ],
      "currentState": "researched-not-authored"
    },
    {
      "id": "html-figures-captions",
      "title": "Figures and captions",
      "objective": "Use figure and figcaption only when self-contained content and its caption form a meaningful relationship.",
      "order": 27,
      "moduleId": "html-images-and-media",
      "prerequisiteIds": [
        "html-images-purpose-alt",
        "html-nesting-tree"
      ],
      "sourceAnchors": [
        {
          "sourceId": "rwd-whatwg-html",
          "locator": "figure and figcaption elements",
          "claim": "HTML defines contextual figure content and caption relationships."
        }
      ],
      "misconceptions": [
        "Every image belongs in a figure and its figcaption replaces alternative text."
      ],
      "evidenceRequirements": [
        "Learner must decide when a figure relationship is warranted and when ordinary flow is clearer.",
        "Accessibility inspection must distinguish caption, alternative text, and surrounding explanation roles."
      ],
      "stages": [
        "introduce",
        "model",
        "guided",
        "faded",
        "debug",
        "retrieve",
        "assess",
        "transfer"
      ],
      "retainedInModuleIds": [
        "html-independent-project"
      ],
      "currentState": "researched-not-authored"
    },
    {
      "id": "html-svg-semantics",
      "title": "SVG embedding and accessible meaning",
      "objective": "Choose inline SVG, external image, or decorative treatment and expose or hide graphic meaning consistently.",
      "order": 28,
      "moduleId": "html-images-and-media",
      "prerequisiteIds": [
        "html-nesting-tree",
        "html-attribute-syntax"
      ],
      "sourceAnchors": [
        {
          "sourceId": "rwd-wai-tutorials",
          "locator": "Images tutorial",
          "claim": "Graphics need purpose-dependent text alternatives and must not duplicate nearby content."
        }
      ],
      "misconceptions": [
        "SVG path data automatically gives assistive technology a useful accessible name."
      ],
      "evidenceRequirements": [
        "Meaningful and decorative changed cases must produce distinct accessibility-tree results.",
        "Learner must justify embedding choice using styling, caching, interaction, security, and accessibility constraints."
      ],
      "stages": [
        "introduce",
        "model",
        "guided",
        "faded",
        "debug",
        "retrieve",
        "assess",
        "transfer"
      ],
      "retainedInModuleIds": [
        "html-independent-project"
      ],
      "currentState": "researched-not-authored"
    },
    {
      "id": "html-audio-video",
      "title": "Native audio and video",
      "objective": "Provide native controls, suitable sources, dimensions where relevant, fallback content, and user-controlled playback.",
      "order": 29,
      "moduleId": "html-images-and-media",
      "prerequisiteIds": [
        "html-files-paths-urls",
        "html-attribute-syntax"
      ],
      "sourceAnchors": [
        {
          "sourceId": "rwd-mdn-curriculum",
          "locator": "Semantic HTML 2.6 media",
          "claim": "MDN includes audio, video, sources, controls, muted behavior, optimization, and licensing."
        }
      ],
      "misconceptions": [
        "A media file that autoplays successfully is accessible without native controls."
      ],
      "evidenceRequirements": [
        "Keyboard and changed-source tests must preserve playback control and fallback information.",
        "Learner must justify autoplay, preload, controls, source, poster, and file-size decisions."
      ],
      "stages": [
        "introduce",
        "model",
        "guided",
        "faded",
        "debug",
        "retrieve",
        "assess",
        "transfer"
      ],
      "retainedInModuleIds": [
        "html-independent-project"
      ],
      "currentState": "researched-not-authored"
    },
    {
      "id": "html-captions-transcripts",
      "title": "Captions, transcripts, and alternatives",
      "objective": "Provide synchronized captions, transcripts, audio description planning, and equivalent fallback according to media content and task.",
      "order": 30,
      "moduleId": "html-images-and-media",
      "prerequisiteIds": [
        "html-audio-video"
      ],
      "sourceAnchors": [
        {
          "sourceId": "rwd-wcag-two-two",
          "locator": "Guideline 1.2 time-based media",
          "claim": "Prerecorded and live media alternatives depend on audio, video, timing, and conformance context."
        }
      ],
      "misconceptions": [
        "Visible subtitles embedded in video always replace a selectable caption track and transcript."
      ],
      "evidenceRequirements": [
        "Changed silent-video, audio-only, and dialogue-plus-visual-detail cases must receive appropriate alternatives.",
        "Learner must verify track availability, labels, language, timing, and transcript access."
      ],
      "stages": [
        "introduce",
        "model",
        "guided",
        "faded",
        "debug",
        "retrieve",
        "assess",
        "transfer"
      ],
      "retainedInModuleIds": [
        "html-independent-project"
      ],
      "currentState": "researched-not-authored"
    },
    {
      "id": "html-iframe-title-permissions",
      "title": "Embedded document boundaries",
      "objective": "Embed a document with an accurate title, minimal permissions, loading fallback, and responsive bounds while preserving origin awareness.",
      "order": 31,
      "moduleId": "html-images-and-media",
      "prerequisiteIds": [
        "html-files-paths-urls",
        "html-attribute-syntax"
      ],
      "sourceAnchors": [
        {
          "sourceId": "rwd-whatwg-html",
          "locator": "iframe element and sandbox attribute",
          "claim": "Embedded browsing contexts have distinct documents, origins, names, permissions, and sandbox capabilities."
        }
      ],
      "misconceptions": [
        "An iframe title changes the title displayed inside the embedded page and grants no accessibility benefit beyond that."
      ],
      "evidenceRequirements": [
        "Accessibility and security inspection must expose embed purpose, origin, sandbox, permissions, and navigation behavior.",
        "Changed untrusted embed case must be refused or constrained rather than granted convenience permissions."
      ],
      "stages": [
        "introduce",
        "model",
        "guided",
        "faded",
        "debug",
        "retrieve",
        "assess",
        "transfer"
      ],
      "retainedInModuleIds": [
        "html-independent-project"
      ],
      "currentState": "researched-not-authored"
    },
    {
      "id": "html-heading-hierarchy",
      "title": "Headings and document hierarchy",
      "objective": "Choose heading ranks from content hierarchy and navigation needs rather than visual size, then verify a coherent outline.",
      "order": 32,
      "moduleId": "html-text-and-semantics",
      "prerequisiteIds": [
        "html-content-models",
        "html-nesting-tree"
      ],
      "sourceAnchors": [
        {
          "sourceId": "rwd-mdn-curriculum",
          "locator": "Semantic HTML 2.2 document structure",
          "claim": "MDN requires logical heading levels and rejects choosing rank for appearance."
        }
      ],
      "misconceptions": [
        "Every section must contain an h1, or only one h1 may ever appear in a conforming document."
      ],
      "evidenceRequirements": [
        "Learner must defend rank choices from a changed content outline with CSS removed.",
        "Heading navigation and accessibility-tree evidence must preserve page and section relationships."
      ],
      "stages": [
        "introduce",
        "model",
        "guided",
        "faded",
        "debug",
        "retrieve",
        "assess",
        "transfer"
      ],
      "retainedInModuleIds": [
        "html-independent-project"
      ],
      "currentState": "researched-not-authored"
    },
    {
      "id": "html-paragraphs-breaks",
      "title": "Paragraphs, line breaks, and thematic breaks",
      "objective": "Use paragraphs, line breaks, and thematic breaks according to prose structure rather than visual spacing.",
      "order": 33,
      "moduleId": "html-text-and-semantics",
      "prerequisiteIds": [
        "html-element-anatomy"
      ],
      "sourceAnchors": [
        {
          "sourceId": "rwd-whatwg-html",
          "locator": "Grouping content elements",
          "claim": "HTML assigns different semantics and content rules to paragraphs, line breaks, and thematic breaks."
        }
      ],
      "misconceptions": [
        "Multiple br elements are the semantic way to create vertical spacing between unrelated blocks."
      ],
      "evidenceRequirements": [
        "Learner must classify changed prose, address-line, poem-line, and topic-shift requirements.",
        "Artifact must preserve meaning with author styles disabled and at changed text length."
      ],
      "stages": [
        "introduce",
        "model",
        "guided",
        "faded",
        "debug",
        "retrieve",
        "assess",
        "transfer"
      ],
      "retainedInModuleIds": [
        "html-independent-project"
      ],
      "currentState": "researched-not-authored"
    },
    {
      "id": "html-lists",
      "title": "Ordered, unordered, and description lists",
      "objective": "Select and correctly nest ordered, unordered, and description lists according to sequence and term-description relationships.",
      "order": 34,
      "moduleId": "html-text-and-semantics",
      "prerequisiteIds": [
        "html-nesting-tree",
        "html-content-models"
      ],
      "sourceAnchors": [
        {
          "sourceId": "rwd-mdn-curriculum",
          "locator": "Semantic HTML 2.3 lists",
          "claim": "MDN distinguishes unordered, ordered, and description lists by relationship and includes navigation use."
        }
      ],
      "misconceptions": [
        "Lists differ only in their default bullet or number styling."
      ],
      "evidenceRequirements": [
        "Changed sequence, collection, glossary, navigation, and nested-list cases must use appropriate structures.",
        "DOM and accessibility evidence must preserve list type, item count, nesting, terms, and descriptions."
      ],
      "stages": [
        "introduce",
        "model",
        "guided",
        "faded",
        "debug",
        "retrieve",
        "assess",
        "transfer"
      ],
      "retainedInModuleIds": [
        "html-independent-project"
      ],
      "currentState": "researched-not-authored"
    },
    {
      "id": "html-emphasis-importance",
      "title": "Emphasis and importance",
      "objective": "Use emphasis, strong importance, and presentationally neutral text according to linguistic meaning rather than desired font style.",
      "order": 35,
      "moduleId": "html-text-and-semantics",
      "prerequisiteIds": [
        "html-element-anatomy",
        "html-content-models"
      ],
      "sourceAnchors": [
        {
          "sourceId": "rwd-mdn-curriculum",
          "locator": "Semantic HTML 2.4 advanced text",
          "claim": "MDN requires correct use of emphasis, importance, and other text-level semantics."
        }
      ],
      "misconceptions": [
        "Strong and em are interchangeable shortcuts for bold and italic appearance."
      ],
      "evidenceRequirements": [
        "Learner must select semantics for changed stress, warning, label, and purely visual requirements.",
        "Artifact must retain intended meaning when author styles and visual emphasis are removed."
      ],
      "stages": [
        "introduce",
        "model",
        "guided",
        "faded",
        "debug",
        "retrieve",
        "assess",
        "transfer"
      ],
      "retainedInModuleIds": [
        "html-independent-project"
      ],
      "currentState": "researched-not-authored"
    },
    {
      "id": "html-quotations-citations",
      "title": "Quotations and citations",
      "objective": "Represent block and inline quotations, sources, and creative-work citations without inventing unsupported provenance.",
      "order": 36,
      "moduleId": "html-text-and-semantics",
      "prerequisiteIds": [
        "html-emphasis-importance"
      ],
      "sourceAnchors": [
        {
          "sourceId": "rwd-mdn-curriculum",
          "locator": "Semantic HTML 2.4 advanced text",
          "claim": "MDN includes quotations and citations among required text semantics."
        }
      ],
      "misconceptions": [
        "The cite element is the correct container for a quoted speaker or any source URL."
      ],
      "evidenceRequirements": [
        "Changed inline quote, long quotation, title, speaker, and source cases must separate content roles.",
        "Learner must verify visible attribution and machine-readable relationships without fabricating metadata."
      ],
      "stages": [
        "introduce",
        "model",
        "guided",
        "faded",
        "debug",
        "retrieve",
        "assess",
        "transfer"
      ],
      "retainedInModuleIds": [
        "html-independent-project"
      ],
      "currentState": "researched-not-authored"
    },
    {
      "id": "html-machine-readable-text",
      "title": "Dates, abbreviations, code, and contact context",
      "objective": "Use time, abbreviation, code-related, address, superscript, subscript, deletion, and insertion semantics where their defined meaning fits.",
      "order": 37,
      "moduleId": "html-text-and-semantics",
      "prerequisiteIds": [
        "html-attribute-syntax",
        "html-emphasis-importance"
      ],
      "sourceAnchors": [
        {
          "sourceId": "rwd-mdn-curriculum",
          "locator": "Semantic HTML 2.4 advanced text",
          "claim": "MDN expects awareness and appropriate use of dates, abbreviations, addresses, code, and related text semantics."
        }
      ],
      "misconceptions": [
        "The address element can mark up any street or postal address wherever it appears."
      ],
      "evidenceRequirements": [
        "Learner must select or reject specialized text semantics in changed editorial contexts.",
        "Machine-readable values must remain valid while visible localized text changes."
      ],
      "stages": [
        "introduce",
        "model",
        "guided",
        "faded",
        "debug",
        "retrieve",
        "assess",
        "transfer"
      ],
      "retainedInModuleIds": [
        "html-independent-project"
      ],
      "currentState": "researched-not-authored"
    },
    {
      "id": "html-landmarks",
      "title": "Page landmarks",
      "objective": "Use header, nav, main, aside, and footer according to page relationships and verify useful non-duplicative landmark navigation.",
      "order": 38,
      "moduleId": "html-text-and-semantics",
      "prerequisiteIds": [
        "html-heading-hierarchy",
        "html-content-models"
      ],
      "sourceAnchors": [
        {
          "sourceId": "rwd-wai-tutorials",
          "locator": "Page structure regions",
          "claim": "Landmarks identify major page regions for navigation when element context and accessible names are appropriate."
        }
      ],
      "misconceptions": [
        "Every header and footer element always creates a banner or contentinfo landmark."
      ],
      "evidenceRequirements": [
        "Accessibility-tree inspection must expose one useful main region and distinguish nested contextual headers and footers.",
        "Changed repeated navigation regions must receive unique purpose or names without redundant landmarks."
      ],
      "stages": [
        "introduce",
        "model",
        "guided",
        "faded",
        "debug",
        "retrieve",
        "assess",
        "transfer"
      ],
      "retainedInModuleIds": [
        "html-independent-project"
      ],
      "currentState": "researched-not-authored"
    },
    {
      "id": "html-sectioning-articles",
      "title": "Sections, articles, and generic groups",
      "objective": "Choose section, article, div, and other groups from content relationships, heading needs, reuse, and semantics rather than styling convenience.",
      "order": 39,
      "moduleId": "html-text-and-semantics",
      "prerequisiteIds": [
        "html-landmarks",
        "html-heading-hierarchy"
      ],
      "sourceAnchors": [
        {
          "sourceId": "rwd-mdn-curriculum",
          "locator": "Semantic HTML 2.2 good document structure",
          "claim": "MDN contrasts generic div containers with semantic structural elements and their accessibility benefits."
        }
      ],
      "misconceptions": [
        "Section is a semantic replacement for every div and automatically fixes document structure."
      ],
      "evidenceRequirements": [
        "Learner must justify grouping choices for changed standalone, thematic, navigation, and styling-only content.",
        "Heading and landmark evidence must match intended relationships without unnecessary regions."
      ],
      "stages": [
        "introduce",
        "model",
        "guided",
        "faded",
        "debug",
        "retrieve",
        "assess",
        "transfer"
      ],
      "retainedInModuleIds": [
        "html-independent-project"
      ],
      "currentState": "researched-not-authored"
    },
    {
      "id": "html-details-summary",
      "title": "Native disclosure",
      "objective": "Use details and summary when native disclosure behavior meets the need, and reject them when menu, dialog, or exclusive selection behavior is required.",
      "order": 40,
      "moduleId": "html-text-and-semantics",
      "prerequisiteIds": [
        "html-nesting-tree",
        "html-content-models"
      ],
      "sourceAnchors": [
        {
          "sourceId": "rwd-whatwg-html",
          "locator": "details and summary elements",
          "claim": "HTML defines disclosure content, summary labeling, and native open state behavior."
        }
      ],
      "misconceptions": [
        "Details and summary are universal replacements for dropdown menus, accordions, and dialogs."
      ],
      "evidenceRequirements": [
        "Learner must choose or reject native disclosure for changed interaction requirements.",
        "Keyboard, focus, open-state, label, and no-script behavior must pass."
      ],
      "stages": [
        "introduce",
        "model",
        "guided",
        "faded",
        "debug",
        "retrieve",
        "assess",
        "transfer"
      ],
      "retainedInModuleIds": [
        "html-independent-project"
      ],
      "currentState": "researched-not-authored"
    },
    {
      "id": "html-native-controls-first",
      "title": "Native interaction before custom roles",
      "objective": "Select native links, buttons, disclosures, and form controls before custom behavior unless a documented user need proves native behavior insufficient.",
      "order": 41,
      "moduleId": "html-text-and-semantics",
      "prerequisiteIds": [
        "html-content-models",
        "html-parser-recovery"
      ],
      "sourceAnchors": [
        {
          "sourceId": "rwd-mdn-curriculum",
          "locator": "Semantic HTML 2.7 interactive elements",
          "claim": "MDN emphasizes native buttons and form elements because browsers provide keyboard, focus, and semantic behavior."
        }
      ],
      "misconceptions": [
        "A div with role button is equivalent to button after adding one click handler."
      ],
      "evidenceRequirements": [
        "Learner must inventory semantics, keyboard, focus, states, submission, and disabled behavior before choosing custom interaction.",
        "Changed pointer-free and script-failure cases must retain the intended task where native behavior can provide it."
      ],
      "stages": [
        "introduce",
        "model",
        "guided",
        "faded",
        "debug",
        "retrieve",
        "assess",
        "transfer"
      ],
      "retainedInModuleIds": [
        "html-independent-project"
      ],
      "currentState": "researched-not-authored"
    },
    {
      "id": "html-form-submission-data",
      "title": "Form purpose and submitted data",
      "objective": "Build a form whose action, method, control names, values, and submit behavior match a bounded data-collection purpose.",
      "order": 42,
      "moduleId": "html-forms",
      "prerequisiteIds": [
        "html-document-root-head-body",
        "html-links-destinations",
        "html-native-controls-first"
      ],
      "sourceAnchors": [
        {
          "sourceId": "rwd-mdn-curriculum",
          "locator": "Semantic HTML 2.7 forms",
          "claim": "MDN includes form submission, GET and POST, control names, values, and native behavior."
        }
      ],
      "misconceptions": [
        "Every visible enabled form value is submitted even when its control has no name."
      ],
      "evidenceRequirements": [
        "Changed submission must produce the expected name-value set and omit disabled or unnamed controls by rule.",
        "Learner must justify method and data minimization without claiming client HTML secures server processing."
      ],
      "stages": [
        "introduce",
        "model",
        "guided",
        "faded",
        "debug",
        "retrieve",
        "assess",
        "transfer"
      ],
      "retainedInModuleIds": [
        "html-independent-project"
      ],
      "currentState": "researched-not-authored"
    },
    {
      "id": "html-form-labels-instructions",
      "title": "Labels, instructions, and descriptions",
      "objective": "Provide persistent labels and programmatic instructions or descriptions so every control purpose and format remains available across states.",
      "order": 43,
      "moduleId": "html-forms",
      "prerequisiteIds": [
        "html-form-submission-data",
        "html-attribute-syntax"
      ],
      "sourceAnchors": [
        {
          "sourceId": "rwd-wai-tutorials",
          "locator": "Forms labels and instructions",
          "claim": "Controls need explicit labels and instructions associated in programmatically determinable ways."
        }
      ],
      "misconceptions": [
        "Placeholder text is an equivalent accessible label because it appears inside the control."
      ],
      "evidenceRequirements": [
        "Accessibility-name and description inspection must identify every changed control without visual proximity.",
        "Labels and shared instructions must remain persistent under zoom, autofill, entered values, and validation errors."
      ],
      "stages": [
        "introduce",
        "model",
        "guided",
        "faded",
        "debug",
        "retrieve",
        "assess",
        "transfer"
      ],
      "retainedInModuleIds": [
        "html-independent-project"
      ],
      "currentState": "researched-not-authored"
    },
    {
      "id": "html-input-types-autocomplete",
      "title": "Input purpose, keyboard, and autocomplete",
      "objective": "Choose input type, autocomplete token, inputmode, name, and value constraints from data meaning without blocking realistic international input.",
      "order": 44,
      "moduleId": "html-forms",
      "prerequisiteIds": [
        "html-form-submission-data",
        "html-form-labels-instructions"
      ],
      "sourceAnchors": [
        {
          "sourceId": "rwd-mdn-curriculum",
          "locator": "Semantic HTML 2.7 common input types",
          "claim": "MDN requires common input types, attributes, validation, and form states."
        }
      ],
      "misconceptions": [
        "Input type only changes appearance and never affects semantics, keyboard, validation, or submission."
      ],
      "evidenceRequirements": [
        "Changed data examples must accept valid edge cases and reject impossible values for the right reason.",
        "Learner must verify accessible purpose, browser keyboard hint, autocomplete behavior, and submitted value separately."
      ],
      "stages": [
        "introduce",
        "model",
        "guided",
        "faded",
        "debug",
        "retrieve",
        "assess",
        "transfer"
      ],
      "retainedInModuleIds": [
        "html-independent-project"
      ],
      "currentState": "researched-not-authored"
    },
    {
      "id": "html-choice-groups",
      "title": "Radio, checkbox, and grouped choices",
      "objective": "Use fieldset, legend, radio names, checkbox independence, labels, and values to expose exclusive and multiple-choice relationships.",
      "order": 45,
      "moduleId": "html-forms",
      "prerequisiteIds": [
        "html-form-labels-instructions",
        "html-input-types-autocomplete"
      ],
      "sourceAnchors": [
        {
          "sourceId": "rwd-wai-tutorials",
          "locator": "Forms grouping controls",
          "claim": "Related controls need group structure and labels that communicate shared purpose and choice relationships."
        }
      ],
      "misconceptions": [
        "Visually adjacent radio buttons automatically form an announced exclusive group."
      ],
      "evidenceRequirements": [
        "Keyboard and accessibility checks must expose group name, option names, state, and exclusive or independent behavior.",
        "Changed default, missing-value, and dynamically reordered choices must submit the intended data."
      ],
      "stages": [
        "introduce",
        "model",
        "guided",
        "faded",
        "debug",
        "retrieve",
        "assess",
        "transfer"
      ],
      "retainedInModuleIds": [
        "html-independent-project"
      ],
      "currentState": "researched-not-authored"
    },
    {
      "id": "html-textarea-select-buttons",
      "title": "Text areas, selections, and button types",
      "objective": "Use textarea, select, option groups, and explicit button types with correct labels, initial values, and submission behavior.",
      "order": 46,
      "moduleId": "html-forms",
      "prerequisiteIds": [
        "html-form-submission-data",
        "html-form-labels-instructions"
      ],
      "sourceAnchors": [
        {
          "sourceId": "rwd-mdn-curriculum",
          "locator": "Semantic HTML 2.7 interactive elements",
          "claim": "MDN includes textarea, select, option, button types, and warns against routine reset buttons."
        }
      ],
      "misconceptions": [
        "A button inside a form does nothing unless a click handler explicitly assigns behavior."
      ],
      "evidenceRequirements": [
        "Changed form must distinguish submit, reset risk, and ordinary button behavior without accidental submission.",
        "Selected, disabled, multiple, placeholder-like, and submitted option states must be verified."
      ],
      "stages": [
        "introduce",
        "model",
        "guided",
        "faded",
        "debug",
        "retrieve",
        "assess",
        "transfer"
      ],
      "retainedInModuleIds": [
        "html-independent-project"
      ],
      "currentState": "researched-not-authored"
    },
    {
      "id": "html-native-validation",
      "title": "Constraint validation",
      "objective": "Apply required, length, range, and pattern constraints only where they match realistic data, then inspect validity and browser behavior.",
      "order": 47,
      "moduleId": "html-forms",
      "prerequisiteIds": [
        "html-input-types-autocomplete",
        "html-textarea-select-buttons"
      ],
      "sourceAnchors": [
        {
          "sourceId": "rwd-mdn-curriculum",
          "locator": "Semantic HTML 2.7 client-side validation",
          "claim": "MDN treats native constraint validation as usability support, not a substitute for server validation."
        }
      ],
      "misconceptions": [
        "The strictest regular expression always improves data quality and secures submitted data."
      ],
      "evidenceRequirements": [
        "Valid diverse and invalid changed cases must produce correct validity states without excluding legitimate users.",
        "Learner must explain client usability, server authority, disabled behavior, and bypass boundaries."
      ],
      "stages": [
        "introduce",
        "model",
        "guided",
        "faded",
        "debug",
        "retrieve",
        "assess",
        "transfer"
      ],
      "retainedInModuleIds": [
        "html-independent-project"
      ],
      "currentState": "researched-not-authored"
    },
    {
      "id": "html-form-errors-recovery",
      "title": "Form error identification and recovery",
      "objective": "Provide specific persistent errors, programmatic relationships, summary or focus strategy, retained valid data, and successful correction.",
      "order": 48,
      "moduleId": "html-forms",
      "prerequisiteIds": [
        "html-form-labels-instructions",
        "html-native-validation"
      ],
      "sourceAnchors": [
        {
          "sourceId": "rwd-wcag-two-two",
          "locator": "Success Criteria 3.3.1 through 3.3.8",
          "claim": "Input errors need identification, instructions, suggestions, prevention, and accessible authentication or redundant-entry treatment by context."
        }
      ],
      "misconceptions": [
        "A red border and failed submission provide sufficient error identification for all users."
      ],
      "evidenceRequirements": [
        "Keyboard, screen-reader, zoom, and changed multi-error cases must identify, locate, explain, and correct every error.",
        "Successful retry must retain unrelated valid values and produce submitted evidence without duplicate side effects."
      ],
      "stages": [
        "introduce",
        "model",
        "guided",
        "faded",
        "debug",
        "retrieve",
        "assess",
        "transfer"
      ],
      "retainedInModuleIds": [
        "html-independent-project"
      ],
      "currentState": "researched-not-authored"
    },
    {
      "id": "html-tables-purpose",
      "title": "Data tables versus layout",
      "objective": "Choose a table only for two-dimensional data relationships and reject table markup for page layout or unrelated item lists.",
      "order": 49,
      "moduleId": "html-tables",
      "prerequisiteIds": [
        "html-lists",
        "html-content-models"
      ],
      "sourceAnchors": [
        {
          "sourceId": "rwd-wai-tutorials",
          "locator": "Tables tutorial purpose",
          "claim": "WAI limits table guidance to grid data and rejects tables as a layout technique."
        }
      ],
      "misconceptions": [
        "Any aligned columns should use table markup because tables guarantee responsive layout."
      ],
      "evidenceRequirements": [
        "Learner must classify changed grid data, layout, comparison cards, and key-value content.",
        "Chosen structure must remain understandable under linearized and alternative rendering."
      ],
      "stages": [
        "introduce",
        "model",
        "guided",
        "faded",
        "debug",
        "retrieve",
        "assess",
        "transfer"
      ],
      "retainedInModuleIds": [
        "html-independent-project"
      ],
      "currentState": "researched-not-authored"
    },
    {
      "id": "html-table-structure",
      "title": "Rows, cells, groups, and captions",
      "objective": "Build table, caption, row groups, rows, header cells, and data cells that preserve intended data dimensions.",
      "order": 50,
      "moduleId": "html-tables",
      "prerequisiteIds": [
        "html-tables-purpose",
        "html-nesting-tree"
      ],
      "sourceAnchors": [
        {
          "sourceId": "rwd-mdn-curriculum",
          "locator": "Semantic HTML 2.8 tables",
          "claim": "MDN includes basic table cells, spanning, groups, captions, and accessible structure."
        }
      ],
      "misconceptions": [
        "Bold text in the first row is equivalent to header-cell semantics."
      ],
      "evidenceRequirements": [
        "Parsed table grid must match changed row, column, span, and group requirements.",
        "Caption and group structure must remain meaningful with author styles disabled."
      ],
      "stages": [
        "introduce",
        "model",
        "guided",
        "faded",
        "debug",
        "retrieve",
        "assess",
        "transfer"
      ],
      "retainedInModuleIds": [
        "html-independent-project"
      ],
      "currentState": "researched-not-authored"
    },
    {
      "id": "html-table-header-associations",
      "title": "Header associations",
      "objective": "Use th, scope, and explicit headers relationships according to simple and complex table structure so each data cell retains context.",
      "order": 51,
      "moduleId": "html-tables",
      "prerequisiteIds": [
        "html-table-structure",
        "html-form-labels-instructions"
      ],
      "sourceAnchors": [
        {
          "sourceId": "rwd-wai-tutorials",
          "locator": "Tables one-header, two-header, and multi-level tutorials",
          "claim": "Header and data cells need programmatic relationships, with explicit associations for complex cases."
        }
      ],
      "misconceptions": [
        "Scope belongs on data cells because it points each value toward its header."
      ],
      "evidenceRequirements": [
        "Representative cell inspection must report correct row and column headers after changed spans or groups.",
        "Learner must choose simple scope or explicit id and headers without overcomplicating a simple table."
      ],
      "stages": [
        "introduce",
        "model",
        "guided",
        "faded",
        "debug",
        "retrieve",
        "assess",
        "transfer"
      ],
      "retainedInModuleIds": [
        "html-independent-project"
      ],
      "currentState": "researched-not-authored"
    },
    {
      "id": "html-native-accessibility-tree",
      "title": "Native semantics and accessibility information",
      "objective": "Trace HTML element, attribute, content, and relationship choices into role, accessible name, description, state, property, and structure evidence.",
      "order": 52,
      "moduleId": "html-accessibility-and-debugging",
      "prerequisiteIds": [
        "html-landmarks",
        "html-form-labels-instructions",
        "html-table-header-associations"
      ],
      "sourceAnchors": [
        {
          "sourceId": "rwd-mdn-curriculum",
          "locator": "Accessibility HTML learning outcomes",
          "claim": "Semantic HTML provides browser accessibility hooks including names, tables, alternatives, keyboard use, and source order."
        }
      ],
      "misconceptions": [
        "Visible text and visual grouping automatically produce the same accessibility information."
      ],
      "evidenceRequirements": [
        "Learner must predict and inspect role, name, description, state, and relationships for changed native markup.",
        "Artifact must remain operable and understandable when visual styling is removed or altered."
      ],
      "stages": [
        "introduce",
        "model",
        "guided",
        "faded",
        "debug",
        "retrieve",
        "assess",
        "transfer"
      ],
      "retainedInModuleIds": [
        "html-independent-project"
      ],
      "currentState": "researched-not-authored"
    },
    {
      "id": "html-source-order-keyboard",
      "title": "Source order and keyboard path",
      "objective": "Keep reading, focus, and interaction order logical from source structure without positive tabindex or visual reordering dependence.",
      "order": 53,
      "moduleId": "html-accessibility-and-debugging",
      "prerequisiteIds": [
        "html-native-controls-first",
        "html-native-accessibility-tree"
      ],
      "sourceAnchors": [
        {
          "sourceId": "rwd-wcag-two-two",
          "locator": "Success Criteria 1.3.2, 2.1.1, 2.4.3, and 2.4.11",
          "claim": "Meaningful sequence, keyboard operation, focus order, and unobscured focus need observable evidence."
        }
      ],
      "misconceptions": [
        "CSS visual order or positive tabindex safely fixes any source-order problem."
      ],
      "evidenceRequirements": [
        "Keyboard-only changed flow must follow meaningful order, expose visible focus, and avoid traps.",
        "Linearized source and accessibility order must preserve task meaning across responsive layouts."
      ],
      "stages": [
        "introduce",
        "model",
        "guided",
        "faded",
        "debug",
        "retrieve",
        "assess",
        "transfer"
      ],
      "retainedInModuleIds": [
        "html-independent-project"
      ],
      "currentState": "researched-not-authored"
    },
    {
      "id": "html-aria-boundary",
      "title": "ARIA role, state, and property boundary",
      "objective": "Use ARIA only when native semantics cannot express a required relationship or state, and supply the complete interaction contract.",
      "order": 54,
      "moduleId": "html-accessibility-and-debugging",
      "prerequisiteIds": [
        "html-native-controls-first",
        "html-native-accessibility-tree"
      ],
      "sourceAnchors": [
        {
          "sourceId": "rwd-aria-apg",
          "locator": "Patterns and practices",
          "claim": "Custom widget roles require coordinated names, states, properties, focus, and keyboard interaction."
        }
      ],
      "misconceptions": [
        "Adding an ARIA role automatically gives a generic element native keyboard behavior and state management."
      ],
      "evidenceRequirements": [
        "Learner must reject unnecessary ARIA and identify missing behavior in partial custom-widget cases.",
        "Any accepted custom pattern must pass complete role, name, state, property, focus, keyboard, and changed-state checks."
      ],
      "stages": [
        "introduce",
        "model",
        "guided",
        "faded",
        "debug",
        "retrieve",
        "assess",
        "transfer"
      ],
      "retainedInModuleIds": [
        "html-independent-project"
      ],
      "currentState": "researched-not-authored"
    },
    {
      "id": "html-validation-inspection",
      "title": "Validation, source, DOM, and accessibility inspection",
      "objective": "Use conformance validation, source, DOM, accessibility, network, and console evidence to locate root cause rather than guess from appearance.",
      "order": 55,
      "moduleId": "html-accessibility-and-debugging",
      "prerequisiteIds": [
        "html-parser-recovery",
        "html-document-root-head-body",
        "html-native-accessibility-tree"
      ],
      "sourceAnchors": [
        {
          "sourceId": "rwd-mdn-curriculum",
          "locator": "Semantic HTML 2.9 debugging",
          "claim": "MDN requires validation, view source, and DOM inspection for markup debugging."
        }
      ],
      "misconceptions": [
        "A clean validator result proves correct semantics, accessibility, links, content, and task behavior."
      ],
      "evidenceRequirements": [
        "Learner must select the evidence surface that can falsify each changed defect hypothesis.",
        "Repair record must distinguish source conformance, parsed behavior, accessibility information, and user-task verification."
      ],
      "stages": [
        "introduce",
        "model",
        "guided",
        "faded",
        "debug",
        "retrieve",
        "assess",
        "transfer"
      ],
      "retainedInModuleIds": [
        "html-independent-project"
      ],
      "currentState": "researched-not-authored"
    },
    {
      "id": "html-changed-case-testing",
      "title": "Changed-content and failure testing",
      "objective": "Test HTML with long and translated text, missing resources, duplicate identifiers, invalid input, keyboard use, zoom, and altered content relationships.",
      "order": 56,
      "moduleId": "html-accessibility-and-debugging",
      "prerequisiteIds": [
        "html-validation-inspection",
        "html-form-errors-recovery",
        "html-table-header-associations"
      ],
      "sourceAnchors": [
        {
          "sourceId": "rwd-wcag-two-two",
          "locator": "Conformance requirements and applicable success criteria",
          "claim": "Accessibility requirements apply to complete processes and responsive variations rather than one ideal screenshot."
        }
      ],
      "misconceptions": [
        "Passing the supplied example proves the markup will survive realistic content and user variation."
      ],
      "evidenceRequirements": [
        "Hidden changed cases must alter content, order, resources, identifiers, input, and viewport without changing the objective.",
        "Learner must explain which invariant each test protects and diagnose at least one rejected near-miss."
      ],
      "stages": [
        "introduce",
        "model",
        "guided",
        "faded",
        "debug",
        "retrieve",
        "assess",
        "transfer"
      ],
      "retainedInModuleIds": [
        "html-independent-project"
      ],
      "currentState": "researched-not-authored"
    },
    {
      "id": "html-independent-transfer-defense",
      "title": "Independent HTML transfer and defense",
      "objective": "Design, build, test, and defend an unfamiliar multi-section HTML information and data-collection artifact from an empty project.",
      "order": 57,
      "moduleId": "html-independent-project",
      "prerequisiteIds": [
        "html-link-purpose-fragments",
        "html-iframe-title-permissions",
        "html-sectioning-articles",
        "html-form-errors-recovery",
        "html-table-header-associations",
        "html-changed-case-testing"
      ],
      "sourceAnchors": [
        {
          "sourceId": "rwd-fcc-v9",
          "locator": "HTML certification project and review blocks",
          "claim": "Current benchmark requires independent HTML project, review, quiz, and cumulative examination evidence."
        },
        {
          "sourceId": "rwd-mdn-curriculum",
          "locator": "Semantic HTML module outcomes",
          "claim": "Core HTML competence spans documents, structure, text, links, media, controls, forms, tables, and debugging."
        }
      ],
      "misconceptions": [
        "Completing a project from a nearly identical workshop starter proves independent HTML transfer."
      ],
      "evidenceRequirements": [
        "Artifact must begin from empty project constraints and pass behavior, accessibility, failure, changed-content, and validation evidence.",
        "Learner must defend element choices, relationships, alternatives, form data, table context, test limits, and remaining uncertainty."
      ],
      "stages": [
        "introduce",
        "model",
        "guided",
        "faded",
        "debug",
        "retrieve",
        "assess",
        "transfer"
      ],
      "retainedInModuleIds": [
        "html-independent-project"
      ],
      "currentState": "researched-not-authored"
    }
  ],
  "architectureFindings": [
    "Current blueprint delays first HTML construction behind thirteen tooling activities; files, browser, DevTools, and research must enter just in time around the first artifact.",
    "Current basic HTML and semantic HTML boundaries separate concepts that depend on one another; proposed modules follow element, document, content, interaction, data, access, and transfer prerequisites.",
    "Current generated activities map all competencies across broad source blocks, but this does not prove each concept receives explicit explanation, malformed cases, fading, debugging, retrieval, or independent transfer.",
    "Current HTML project follows existing generated work and cannot count as transfer until its scenario, empty starter, requirements, grading, and defense differ meaningfully from instruction."
  ],
  "gaps": [
    "Subject-matter review must verify each locator, standards claim, prerequisite edge, misconception, and scope boundary.",
    "Instructional and assessment review must map each concept into original activities and inspect full evidence progression.",
    "Accessibility review and representative beginner observation must test the sequence, editor, feedback, recovery, and independent project.",
    "HTML-to-CSS cross-boundary prerequisites and exact alignment to all pinned v9 objectives require reviewer closure before the complete course dossier can enter review."
  ]
}
