{
  "schemaVersion": 2,
  "id": "linux-packages-provenance",
  "courseId": "linux-basics",
  "title": "Packages, Repositories, Dependencies, and Software Provenance",
  "description": "Install or update a required tool while preserving repository trust, version evidence, rollback options, and the boundary between system and project dependencies. Learners cumulatively produce a distribution-aware package change record through theory, guided work, debugging, transfer, retrieval, and assessment.",
  "order": 9,
  "sourceObjectiveIds": [],
  "objectives": [
    "Distinguish repositories, metadata, packages, dependencies, installed files, scripts, and transaction history.",
    "Query package origin, version, architecture, files, dependencies, reverse dependencies, and candidate changes before mutation.",
    "Evaluate repository ownership, signing keys, transport, scope, pinning, and update policy before adding a source."
  ],
  "competencyIds": [
    "linux-package-manager-model",
    "linux-secret-environment-risk",
    "linux-package-query",
    "linux-repository-trust",
    "linux-system-project-dependencies",
    "linux-package-rollback"
  ],
  "prerequisites": [
    "linux-environment-startup"
  ],
  "activityIds": [
    "linux-packages-provenance-linux-package-manager-model-concept",
    "linux-packages-provenance-linux-package-query-concept",
    "linux-packages-provenance-linux-repository-trust-concept",
    "linux-packages-provenance-linux-system-project-dependencies-concept",
    "linux-packages-provenance-linux-package-rollback-concept",
    "linux-packages-provenance-guided-workshop",
    "linux-packages-provenance-debugging-clinic",
    "linux-packages-provenance-independent-lab",
    "linux-packages-provenance-retrieval-review",
    "linux-packages-provenance-mastery-quiz"
  ]
}
