{
  "schemaVersion": 2,
  "id": "sql-filtering-logic-order",
  "courseId": "sql-basics",
  "title": "Filtering, Three-Valued Logic, Patterns, Ordering, and Pagination",
  "description": "A queue view must include the correct unresolved tickets, handle missing owners, and remain deterministic across pages. Learners cumulatively produce a deterministic queue-filter query suite through theory, guided work, debugging, transfer, retrieval, and assessment.",
  "order": 4,
  "objectives": [
    "Combine comparison, range, membership, and boolean predicates with explicit grouping.",
    "Predict TRUE, FALSE, and UNKNOWN through comparisons and boolean operators involving NULL.",
    "Use IS NULL, IS NOT NULL, COALESCE, and NULLIF only when their business meaning is justified."
  ],
  "competencyIds": [
    "sql-where-predicates",
    "sql-distinct-duplicates",
    "sql-three-valued-logic",
    "sql-null-predicates",
    "sql-pattern-filtering",
    "sql-order-limit-pagination"
  ],
  "prerequisites": [
    "sql-select-expressions-types"
  ],
  "activityIds": [
    "sql-filtering-logic-order-sql-where-predicates-concept",
    "sql-filtering-logic-order-sql-three-valued-logic-concept",
    "sql-filtering-logic-order-sql-null-predicates-concept",
    "sql-filtering-logic-order-sql-pattern-filtering-concept",
    "sql-filtering-logic-order-sql-order-limit-pagination-concept",
    "sql-filtering-logic-order-guided-workshop",
    "sql-filtering-logic-order-debugging-clinic",
    "sql-filtering-logic-order-independent-lab",
    "sql-filtering-logic-order-retrieval-review",
    "sql-filtering-logic-order-mastery-quiz"
  ]
}
