{
  "id": "quiz-01-chapter-1",
  "courseId": "python-oop",
  "chapterId": "ch1-clean-code",
  "title": "Chapter 1: Clean Code Principles - Quiz",
  "description": "Comprehensive test of clean code principles, Pythonic code, DRY, KISS, YAGNI, and refactoring",
  "passingScore": 75,
  "timeLimit": 3600,
  "questions": [
    {
      "id": "q1",
      "question": "What does DRY stand for in software development?",
      "type": "multiple-choice",
      "points": 10,
      "options": [
        {"id": "a", "text": "Don't Repeat Yourself"},
        {"id": "b", "text": "Do Run Yearly"},
        {"id": "c", "text": "Data Requires Yield"},
        {"id": "d", "text": "Dynamic Reusable Yearly"}
      ],
      "correctAnswer": "a",
      "explanation": "DRY stands for Don't Repeat Yourself - a principle that aims to reduce code duplication."
    },
    {
      "id": "q2",
      "question": "What is the PEP 8 recommended naming convention for variables?",
      "type": "multiple-choice",
      "points": 10,
      "options": [
        {"id": "a", "text": "camelCase"},
        {"id": "b", "text": "snake_case"},
        {"id": "c", "text": "PascalCase"},
        {"id": "d", "text": "kebab-case"}
      ],
      "correctAnswer": "b",
      "explanation": "PEP 8 recommends snake_case (lowercase with underscores) for variable and function names."
    },
    {
      "id": "q3",
      "question": "What does KISS principle mean?",
      "type": "multiple-choice",
      "points": 10,
      "options": [
        {"id": "a", "text": "Keep It Simple, Stupid"},
        {"id": "b", "text": "Keep Iterating Simple Solutions"},
        {"id": "c", "text": "Know Important System Structures"},
        {"id": "d", "text": "Keep Input Simple Syntax"}
      ],
      "correctAnswer": "a",
      "explanation": "KISS stands for Keep It Simple, Stupid - favoring simplicity over complexity."
    },
    {
      "id": "q4",
      "question": "What does YAGNI stand for?",
      "type": "multiple-choice",
      "points": 10,
      "options": [
        {"id": "a", "text": "You Always Get New Ideas"},
        {"id": "b", "text": "You Aren't Gonna Need It"},
        {"id": "c", "text": "Yet Another General Network Interface"},
        {"id": "d", "text": "Your Application Gets New Iterations"}
      ],
      "correctAnswer": "b",
      "explanation": "YAGNI stands for You Aren't Gonna Need It - don't add functionality until it's actually needed."
    },
    {
      "id": "q5",
      "question": "What is the recommended maximum line length in PEP 8?",
      "type": "multiple-choice",
      "points": 10,
      "options": [
        {"id": "a", "text": "72 characters"},
        {"id": "b", "text": "79 characters"},
        {"id": "c", "text": "100 characters"},
        {"id": "d", "text": "120 characters"}
      ],
      "correctAnswer": "b",
      "explanation": "PEP 8 recommends a maximum line length of 79 characters for code."
    },
    {
      "id": "q6",
      "question": "Which naming convention is used for class names in Python?",
      "type": "multiple-choice",
      "points": 10,
      "options": [
        {"id": "a", "text": "snake_case"},
        {"id": "b", "text": "camelCase"},
        {"id": "c", "text": "PascalCase"},
        {"id": "d", "text": "UPPER_CASE"}
      ],
      "correctAnswer": "c",
      "explanation": "PEP 8 recommends PascalCase (CapWords) for class names."
    },
    {
      "id": "q7",
      "question": "What is the output?\n```python\nif True:\n    print('Hello')\n```",
      "type": "multiple-choice",
      "points": 10,
      "options": [
        {"id": "a", "text": "Hello"},
        {"id": "b", "text": "True"},
        {"id": "c", "text": "Error"},
        {"id": "d", "text": "Nothing"}
      ],
      "correctAnswer": "a",
      "explanation": "The condition is True, so 'Hello' is printed."
    },
    {
      "id": "q8",
      "question": "Which is more Pythonic?\n```python\n# Option A\nif x == True:\n    pass\n\n# Option B\nif x:\n    pass\n```",
      "type": "multiple-choice",
      "points": 10,
      "options": [
        {"id": "a", "text": "Option A"},
        {"id": "b", "text": "Option B"},
        {"id": "c", "text": "Both equal"},
        {"id": "d", "text": "Neither"}
      ],
      "correctAnswer": "b",
      "explanation": "Option B is more Pythonic - use truthiness directly without comparing to True."
    },
    {
      "id": "q9",
      "question": "What does refactoring mean?",
      "type": "multiple-choice",
      "points": 10,
      "options": [
        {"id": "a", "text": "Rewriting code from scratch"},
        {"id": "b", "text": "Improving code structure without changing behavior"},
        {"id": "c", "text": "Adding new features"},
        {"id": "d", "text": "Deleting old code"}
      ],
      "correctAnswer": "b",
      "explanation": "Refactoring improves code structure and readability without changing external behavior."
    },
    {
      "id": "q10",
      "question": "What is the Single Responsibility Principle?",
      "type": "multiple-choice",
      "points": 10,
      "options": [
        {"id": "a", "text": "A class should have only one reason to change"},
        {"id": "b", "text": "A class should have only one method"},
        {"id": "c", "text": "A class should have only one attribute"},
        {"id": "d", "text": "A class should have only one instance"}
      ],
      "correctAnswer": "a",
      "explanation": "SRP states that a class should have only one reason to change - one responsibility."
    },
    {
      "id": "q11",
      "question": "Which import style is preferred?",
      "type": "multiple-choice",
      "points": 10,
      "options": [
        {"id": "a", "text": "from module import *"},
        {"id": "b", "text": "import module"},
        {"id": "c", "text": "import * from module"},
        {"id": "d", "text": "require module"}
      ],
      "correctAnswer": "b",
      "explanation": "Explicit imports are preferred over wildcard imports for clarity and namespace control."
    },
    {
      "id": "q12",
      "question": "What is code smell?",
      "type": "multiple-choice",
      "points": 10,
      "options": [
        {"id": "a", "text": "Syntax errors"},
        {"id": "b", "text": "Indicators of potential problems in code"},
        {"id": "c", "text": "Comments in code"},
        {"id": "d", "text": "Type errors"}
      ],
      "correctAnswer": "b",
      "explanation": "Code smell refers to patterns that indicate potential design or implementation problems."
    },
    {
      "id": "q13",
      "question": "How should constants be named in Python?",
      "type": "multiple-choice",
      "points": 10,
      "options": [
        {"id": "a", "text": "camelCase"},
        {"id": "b", "text": "snake_case"},
        {"id": "c", "text": "ALL_CAPS"},
        {"id": "d", "text": "PascalCase"}
      ],
      "correctAnswer": "c",
      "explanation": "Constants use ALL_CAPS with underscores to indicate they should not be changed."
    },
    {
      "id": "q14",
      "question": "What does separation of concerns mean?",
      "type": "multiple-choice",
      "points": 10,
      "options": [
        {"id": "a", "text": "Separating different functionalities into distinct sections"},
        {"id": "b", "text": "Using separate files for each function"},
        {"id": "c", "text": "Writing comments for each concern"},
        {"id": "d", "text": "Using separate variables"}
      ],
      "correctAnswer": "a",
      "explanation": "Separation of concerns means dividing a program into distinct sections that address separate concerns."
    },
    {
      "id": "q15",
      "question": "Which is better for checking empty list?",
      "type": "multiple-choice",
      "points": 10,
      "options": [
        {"id": "a", "text": "if len(my_list) == 0:"},
        {"id": "b", "text": "if not my_list:"},
        {"id": "c", "text": "if my_list == []:"},
        {"id": "d", "text": "All equal"}
      ],
      "correctAnswer": "b",
      "explanation": "Using 'if not my_list:' is more Pythonic - leverages truthiness of empty sequences."
    },
    {
      "id": "q16",
      "question": "What is technical debt?",
      "type": "multiple-choice",
      "points": 10,
      "options": [
        {"id": "a", "text": "Money owed for software licenses"},
        {"id": "b", "text": "Future cost of rework from shortcuts taken"},
        {"id": "c", "text": "Time spent learning new technologies"},
        {"id": "d", "text": "Cost of hiring developers"}
      ],
      "correctAnswer": "b",
      "explanation": "Technical debt is the implied cost of additional rework caused by choosing quick solutions."
    },
    {
      "id": "q17",
      "question": "What is the Zen of Python?",
      "type": "multiple-choice",
      "points": 10,
      "options": [
        {"id": "a", "text": "A meditation technique"},
        {"id": "b", "text": "A collection of design principles (PEP 20)"},
        {"id": "c", "text": "A testing framework"},
        {"id": "d", "text": "A debugging tool"}
      ],
      "correctAnswer": "b",
      "explanation": "The Zen of Python (PEP 20) contains 19 guiding principles for Python design."
    },
    {
      "id": "q18",
      "question": "Which violates DRY principle?",
      "type": "multiple-choice",
      "points": 10,
      "options": [
        {"id": "a", "text": "Using functions"},
        {"id": "b", "text": "Copy-pasting code"},
        {"id": "c", "text": "Using variables"},
        {"id": "d", "text": "Using classes"}
      ],
      "correctAnswer": "b",
      "explanation": "Copy-pasting code creates duplication, violating the DRY principle."
    },
    {
      "id": "q19",
      "question": "What is premature optimization?",
      "type": "multiple-choice",
      "points": 10,
      "options": [
        {"id": "a", "text": "Optimizing before identifying actual bottlenecks"},
        {"id": "b", "text": "Optimizing too late"},
        {"id": "c", "text": "Not optimizing at all"},
        {"id": "d", "text": "Optimizing everything"}
      ],
      "correctAnswer": "a",
      "explanation": "Premature optimization is optimizing before knowing what actually needs optimization."
    },
    {
      "id": "q20",
      "question": "What should code comments explain?",
      "type": "multiple-choice",
      "points": 10,
      "options": [
        {"id": "a", "text": "What the code does"},
        {"id": "b", "text": "Why the code exists"},
        {"id": "c", "text": "How to run the code"},
        {"id": "d", "text": "When it was written"}
      ],
      "correctAnswer": "b",
      "explanation": "Comments should explain 'why' - the code itself should be clear about 'what' it does."
    },
    {
      "id": "q21",
      "question": "Code should be written for machines to execute.",
      "type": "true-false",
      "points": 10,
      "correctAnswer": false,
      "explanation": "Code should be written for humans to read and understand; machines will execute it regardless."
    },
    {
      "id": "q22",
      "question": "PEP 8 is mandatory for all Python code.",
      "type": "true-false",
      "points": 10,
      "correctAnswer": false,
      "explanation": "PEP 8 is a style guide, not a requirement, but consistency within a project is important."
    },
    {
      "id": "q23",
      "question": "Refactoring should change the external behavior of code.",
      "type": "true-false",
      "points": 10,
      "correctAnswer": false,
      "explanation": "Refactoring improves internal structure without changing external behavior or functionality."
    },
    {
      "id": "q24",
      "question": "Functions should do one thing and do it well.",
      "type": "true-false",
      "points": 10,
      "correctAnswer": true,
      "explanation": "This follows the Single Responsibility Principle - each function should have one clear purpose."
    },
    {
      "id": "q25",
      "question": "Long variable names are always better than short ones.",
      "type": "true-false",
      "points": 10,
      "correctAnswer": false,
      "explanation": "Variable names should be descriptive but not unnecessarily long; context matters."
    },
    {
      "id": "q26",
      "question": "Magic numbers should be replaced with named constants.",
      "type": "true-false",
      "points": 10,
      "correctAnswer": true,
      "explanation": "Named constants make code more readable and maintainable than unexplained numbers."
    },
    {
      "id": "q27",
      "question": "Clever code is better than readable code.",
      "type": "true-false",
      "points": 10,
      "correctAnswer": false,
      "explanation": "The Zen of Python states 'Readability counts' - clarity trumps cleverness."
    },
    {
      "id": "q28",
      "question": "All code should be documented with comments.",
      "type": "true-false",
      "points": 10,
      "correctAnswer": false,
      "explanation": "Self-documenting code is better; comments should explain 'why', not obvious 'what'."
    },
    {
      "id": "q29",
      "question": "Pythonic code prioritizes readability over performance.",
      "type": "true-false",
      "points": 10,
      "correctAnswer": true,
      "explanation": "Python values readability; optimize only after identifying actual performance issues."
    },
    {
      "id": "q30",
      "question": "Global variables should be avoided when possible.",
      "type": "true-false",
      "points": 10,
      "correctAnswer": true,
      "explanation": "Global variables can make code harder to understand and maintain; prefer local scope."
    },
    {
      "id": "q31",
      "question": "Which are clean code principles? (Select all that apply)",
      "type": "multiple-select",
      "points": 15,
      "options": [
        {"id": "a", "text": "DRY"},
        {"id": "b", "text": "KISS"},
        {"id": "c", "text": "YAGNI"},
        {"id": "d", "text": "WET (Write Everything Twice)"}
      ],
      "correctAnswers": ["a", "b", "c"],
      "explanation": "DRY, KISS, and YAGNI are clean code principles. WET is an anti-pattern."
    },
    {
      "id": "q32",
      "question": "Which naming conventions are correct per PEP 8? (Select all)",
      "type": "multiple-select",
      "points": 15,
      "options": [
        {"id": "a", "text": "my_variable (variable)"},
        {"id": "b", "text": "MyClass (class)"},
        {"id": "c", "text": "MY_CONSTANT (constant)"},
        {"id": "d", "text": "myFunction (function)"}
      ],
      "correctAnswers": ["a", "b", "c"],
      "explanation": "Variables/functions use snake_case, classes use PascalCase, constants use ALL_CAPS."
    },
    {
      "id": "q33",
      "question": "Which are code smells? (Select all that apply)",
      "type": "multiple-select",
      "points": 15,
      "options": [
        {"id": "a", "text": "Long functions"},
        {"id": "b", "text": "Duplicated code"},
        {"id": "c", "text": "Magic numbers"},
        {"id": "d", "text": "Descriptive names"}
      ],
      "correctAnswers": ["a", "b", "c"],
      "explanation": "Long functions, duplicated code, and magic numbers are code smells. Descriptive names are good."
    },
    {
      "id": "q34",
      "question": "Which should be avoided? (Select all that apply)",
      "type": "multiple-select",
      "points": 15,
      "options": [
        {"id": "a", "text": "Deep nesting"},
        {"id": "b", "text": "Large functions"},
        {"id": "c", "text": "Descriptive variable names"},
        {"id": "d", "text": "Code duplication"}
      ],
      "correctAnswers": ["a", "b", "d"],
      "explanation": "Avoid deep nesting, large functions, and duplication. Descriptive names are encouraged."
    },
    {
      "id": "q35",
      "question": "Which are principles from the Zen of Python? (Select all)",
      "type": "multiple-select",
      "points": 15,
      "options": [
        {"id": "a", "text": "Readability counts"},
        {"id": "b", "text": "Simple is better than complex"},
        {"id": "c", "text": "Explicit is better than implicit"},
        {"id": "d", "text": "Complexity is best"}
      ],
      "correctAnswers": ["a", "b", "c"],
      "explanation": "These are from PEP 20. The Zen favors simplicity over complexity."
    },
    {
      "id": "q36",
      "question": "Complete: Pythonic way to check empty list",
      "type": "code-completion",
      "points": 15,
      "starterCode": "my_list = []\nif ____ my_list:\n    print('Empty')",
      "correctAnswer": "if not my_list:",
      "acceptableAnswers": ["not", "if not my_list:", "not my_list"],
      "explanation": "Use 'if not my_list:' to check for empty sequences Pythonically.",
      "language": "python"
    },
    {
      "id": "q37",
      "question": "Complete: Define a constant",
      "type": "code-completion",
      "points": 15,
      "starterCode": "____ = 3.14159",
      "correctAnswer": "PI = 3.14159",
      "acceptableAnswers": ["PI", "PI = 3.14159", "PI=3.14159"],
      "explanation": "Constants use ALL_CAPS naming convention.",
      "language": "python"
    },
    {
      "id": "q38",
      "question": "Complete: Pythonic iteration",
      "type": "code-completion",
      "points": 15,
      "starterCode": "items = [1, 2, 3]\nfor item ____ items:\n    print(item)",
      "correctAnswer": "for item in items:",
      "acceptableAnswers": ["in", "for item in items:", "in items"],
      "explanation": "Use 'in' for Pythonic iteration over sequences.",
      "language": "python"
    },
    {
      "id": "q39",
      "question": "Complete: Swap variables Pythonically",
      "type": "code-completion",
      "points": 15,
      "starterCode": "a = 1\nb = 2\n____, ____ = ____, ____",
      "correctAnswer": "a, b = b, a",
      "acceptableAnswers": ["a, b = b, a", "a,b=b,a"],
      "explanation": "Python allows tuple unpacking for elegant variable swapping.",
      "language": "python"
    },
    {
      "id": "q40",
      "question": "Complete: List comprehension",
      "type": "code-completion",
      "points": 15,
      "starterCode": "numbers = [1, 2, 3, 4, 5]\nsquared = [____ for ____ in numbers]",
      "correctAnswer": "squared = [x**2 for x in numbers]",
      "acceptableAnswers": ["x**2 for x in numbers", "x**2", "n**2 for n in numbers"],
      "explanation": "List comprehension: [expression for item in iterable]",
      "language": "python"
    },
    {
      "id": "q41",
      "question": "Refactor to DRY Principle",
      "type": "coding-exercise",
      "points": 20,
      "description": "Refactor this duplicated code using a function:\n```python\nprint('User: Alice')\nprint('Age: 25')\nprint('---')\nprint('User: Bob')\nprint('Age: 30')\nprint('---')\n```",
      "starterCode": "# Create function to eliminate duplication\n",
      "language": "python",
      "testCases": [
        {
          "id": "t1",
          "description": "Function prints user info",
          "expectedOutput": "User: Alice\\nAge: 25\\n---",
          "isHidden": false
        }
      ],
      "hints": ["Create print_user(name, age) function", "Call function for each user"]
    },
    {
      "id": "q42",
      "question": "Apply KISS Principle",
      "type": "coding-exercise",
      "points": 20,
      "description": "Simplify this overcomplicated even checker:\n```python\ndef is_even(n):\n    if n % 2 == 0:\n        return True\n    else:\n        return False\n```",
      "starterCode": "def is_even(n):\n    # Simplify this\n    pass\n",
      "language": "python",
      "testCases": [
        {
          "id": "t1",
          "description": "Returns True for even numbers",
          "expectedOutput": "True",
          "isHidden": false
        }
      ],
      "hints": ["Return the boolean expression directly", "return n % 2 == 0"]
    },
    {
      "id": "q43",
      "question": "Use List Comprehension",
      "type": "coding-exercise",
      "points": 20,
      "description": "Refactor to use list comprehension:\n```python\nsquared = []\nfor num in [1,2,3,4,5]:\n    squared.append(num**2)\n```",
      "starterCode": "numbers = [1, 2, 3, 4, 5]\n# Use list comprehension\nsquared = \n",
      "language": "python",
      "testCases": [
        {
          "id": "t1",
          "description": "Creates [1, 4, 9, 16, 25]",
          "expectedOutput": "[1, 4, 9, 16, 25]",
          "isHidden": false
        }
      ],
      "hints": ["squared = [x**2 for x in numbers]"]
    },
    {
      "id": "q44",
      "question": "Replace Magic Numbers",
      "type": "coding-exercise",
      "points": 20,
      "description": "Replace magic numbers with named constants:\n```python\nif age >= 18:\n    print('Adult')\nif score >= 60:\n    print('Pass')\n```",
      "starterCode": "# Define constants\n\nage = 20\nscore = 75\n",
      "language": "python",
      "testCases": [
        {
          "id": "t1",
          "description": "Uses named constants",
          "expectedOutput": "Adult\\nPass",
          "isHidden": false
        }
      ],
      "hints": ["ADULT_AGE = 18", "PASSING_SCORE = 60", "Use in conditions"]
    },
    {
      "id": "q45",
      "question": "Improve Variable Names",
      "type": "coding-exercise",
      "points": 20,
      "description": "Improve these variable names:\n```python\na = 5\nb = 10\nc = a + b\nprint(c)\n```",
      "starterCode": "# Use descriptive names\n",
      "language": "python",
      "testCases": [
        {
          "id": "t1",
          "description": "Calculates total",
          "expectedOutput": "15",
          "isHidden": false
        }
      ],
      "hints": ["Use names like price, quantity, total", "Be descriptive"]
    },
    {
      "id": "q46",
      "question": "Clean Code Fundamentals - Multi-Part",
      "type": "multi-part",
      "points": 20,
      "parts": [
        {
          "id": "q46a",
          "type": "multiple-choice",
          "question": "What does DRY mean?",
          "points": 7,
          "options": [
            {"id": "a", "text": "Don't Repeat Yourself"},
            {"id": "b", "text": "Do Run Yearly"},
            {"id": "c", "text": "Data Requires Yield"},
            {"id": "d", "text": "Dynamic Reusable Yearly"}
          ],
          "correctAnswer": "a",
          "explanation": "DRY stands for Don't Repeat Yourself."
        },
        {
          "id": "q46b",
          "type": "true-false",
          "question": "KISS means Keep It Simple, Stupid",
          "points": 7,
          "correctAnswer": true,
          "explanation": "KISS principle favors simplicity over complexity."
        },
        {
          "id": "q46c",
          "type": "code-completion",
          "question": "Complete Pythonic check",
          "points": 6,
          "starterCode": "if ____ x:\n    print('Truthy')",
          "correctAnswer": "if x:",
          "acceptableAnswers": ["if x:", "x", ""],
          "explanation": "Check truthiness directly without comparison.",
          "language": "python"
        }
      ]
    },
    {
      "id": "q47",
      "question": "PEP 8 Conventions - Multi-Part",
      "type": "multi-part",
      "points": 20,
      "parts": [
        {
          "id": "q47a",
          "type": "multiple-choice",
          "question": "Variable naming convention?",
          "points": 7,
          "options": [
            {"id": "a", "text": "camelCase"},
            {"id": "b", "text": "snake_case"},
            {"id": "c", "text": "PascalCase"},
            {"id": "d", "text": "kebab-case"}
          ],
          "correctAnswer": "b",
          "explanation": "Variables use snake_case per PEP 8."
        },
        {
          "id": "q47b",
          "type": "multiple-select",
          "question": "Valid PEP 8 names? (Select all)",
          "points": 7,
          "options": [
            {"id": "a", "text": "my_var (variable)"},
            {"id": "b", "text": "MyClass (class)"},
            {"id": "c", "text": "MY_CONST (constant)"},
            {"id": "d", "text": "myFunc (function)"}
          ],
          "correctAnswers": ["a", "b", "c"],
          "explanation": "Functions also use snake_case, not camelCase."
        },
        {
          "id": "q47c",
          "type": "true-false",
          "question": "Max line length is 79 characters",
          "points": 6,
          "correctAnswer": true,
          "explanation": "PEP 8 recommends 79 characters for code lines."
        }
      ]
    },
    {
      "id": "q48",
      "question": "Refactoring Concepts - Multi-Part",
      "type": "multi-part",
      "points": 20,
      "parts": [
        {
          "id": "q48a",
          "type": "true-false",
          "question": "Refactoring changes external behavior",
          "points": 7,
          "correctAnswer": false,
          "explanation": "Refactoring improves structure without changing behavior."
        },
        {
          "id": "q48b",
          "type": "multiple-choice",
          "question": "What is a code smell?",
          "points": 7,
          "options": [
            {"id": "a", "text": "Syntax error"},
            {"id": "b", "text": "Indicator of problems"},
            {"id": "c", "text": "Comment"},
            {"id": "d", "text": "Type error"}
          ],
          "correctAnswer": "b",
          "explanation": "Code smell indicates potential design problems."
        },
        {
          "id": "q48c",
          "type": "multiple-select",
          "question": "Code smells? (Select all)",
          "points": 6,
          "options": [
            {"id": "a", "text": "Long functions"},
            {"id": "b", "text": "Duplicated code"},
            {"id": "c", "text": "Magic numbers"},
            {"id": "d", "text": "Clear names"}
          ],
          "correctAnswers": ["a", "b", "c"],
          "explanation": "Long functions, duplication, and magic numbers are smells."
        }
      ]
    },
    {
      "id": "q49",
      "question": "Pythonic Patterns - Multi-Part",
      "type": "multi-part",
      "points": 20,
      "parts": [
        {
          "id": "q49a",
          "type": "code-completion",
          "question": "Pythonic empty check",
          "points": 7,
          "starterCode": "if ____ my_list:",
          "correctAnswer": "if not my_list:",
          "acceptableAnswers": ["not", "not my_list"],
          "explanation": "Use 'not' with truthiness check.",
          "language": "python"
        },
        {
          "id": "q49b",
          "type": "code-completion",
          "question": "List comprehension",
          "points": 7,
          "starterCode": "[____ for x in range(5)]",
          "correctAnswer": "[x for x in range(5)]",
          "acceptableAnswers": ["x", "x for x in range(5)"],
          "explanation": "Basic list comprehension syntax.",
          "language": "python"
        },
        {
          "id": "q49c",
          "type": "true-false",
          "question": "List comprehensions are Pythonic",
          "points": 6,
          "correctAnswer": true,
          "explanation": "List comprehensions are a Pythonic idiom."
        }
      ]
    },
    {
      "id": "q50",
      "question": "Best Practices - Multi-Part",
      "type": "multi-part",
      "points": 20,
      "parts": [
        {
          "id": "q50a",
          "type": "multiple-select",
          "question": "Clean code principles? (Select all)",
          "points": 7,
          "options": [
            {"id": "a", "text": "DRY"},
            {"id": "b", "text": "KISS"},
            {"id": "c", "text": "YAGNI"},
            {"id": "d", "text": "WET"}
          ],
          "correctAnswers": ["a", "b", "c"],
          "explanation": "DRY, KISS, YAGNI are principles. WET is anti-pattern."
        },
        {
          "id": "q50b",
          "type": "true-false",
          "question": "Comments should explain 'why' not 'what'",
          "points": 7,
          "correctAnswer": true,
          "explanation": "Code should be self-documenting for 'what'; comments explain 'why'."
        },
        {
          "id": "q50c",
          "type": "multiple-choice",
          "question": "What is technical debt?",
          "points": 6,
          "options": [
            {"id": "a", "text": "Software license cost"},
            {"id": "b", "text": "Future rework cost"},
            {"id": "c", "text": "Learning time"},
            {"id": "d", "text": "Hiring cost"}
          ],
          "correctAnswer": "b",
          "explanation": "Technical debt is future cost of rework from shortcuts."
        }
      ]
    }
  ]
}
