{
  "id": "exercise-046-extending-behavior",
  "courseId": "python-oop",
  "lessonId": "lesson-046-extending-behavior",
  "title": "Extend Parent Behavior",
  "description": "Call parent method and extend it",
  "difficulty": "intermediate",
  "points": 25,
  "language": "python",
  "starterCode": "class Logger:\n    def log(self, message):\n        print(f\"LOG: {message}\")\n\n# Create TimestampLogger that calls super().log() and adds timestamp\n\nlogger = TimestampLogger()\nlogger.log(\"Error occurred\")",
  "solution": "class Logger:\n    def log(self, message):\n        print(f\"LOG: {message}\")\n\nclass TimestampLogger(Logger):\n    def log(self, message):\n        super().log(message)\n        print(\"[2024-01-15 10:30:00]\")\n\nlogger = TimestampLogger()\nlogger.log(\"Error occurred\")",
  "hints": [
    "Call super().log(message) first",
    "Then add timestamp behavior",
    "This extends parent behavior",
    "Both parent and child code execute"
  ],
  "testCases": [
    {
      "id": "tc1",
      "description": "Should log with timestamp",
      "input": "",
      "expectedOutput": "LOG: Error occurred\n[2024-01-15 10:30:00]",
      "isHidden": false
    }
  ]
}
