{
  "id": "quiz-06-chapter-6",
  "courseId": "python-basics",
  "chapterId": "ch6-computing",
  "title": "Computing Fundamentals Quiz",
  "passingScore": 70,
  "questions": [
    {
      "id": "q1",
      "question": "What does CPU stand for?",
      "type": "multiple-choice",
      "points": 10,
      "options": [
        {
          "id": "a",
          "text": "Central Processing Unit"
        },
        {
          "id": "b",
          "text": "Computer Power Unit"
        },
        {
          "id": "c",
          "text": "Core Programming Unit"
        },
        {
          "id": "d",
          "text": "Central Program Utility"
        }
      ],
      "correctAnswer": "a",
      "explanation": "The correct answer explains the concept tested in this question."
    },
    {
      "id": "q2",
      "question": "Which is faster but temporary?",
      "type": "multiple-choice",
      "points": 10,
      "options": [
        {
          "id": "a",
          "text": "Hard drive"
        },
        {
          "id": "b",
          "text": "RAM"
        },
        {
          "id": "c",
          "text": "SSD"
        },
        {
          "id": "d",
          "text": "USB drive"
        }
      ],
      "correctAnswer": "b",
      "explanation": "The correct answer explains the concept tested in this question."
    },
    {
      "id": "q3",
      "question": "How many bits are in one byte?",
      "type": "multiple-choice",
      "points": 10,
      "options": [
        {
          "id": "a",
          "text": "4"
        },
        {
          "id": "b",
          "text": "8"
        },
        {
          "id": "c",
          "text": "16"
        },
        {
          "id": "d",
          "text": "32"
        }
      ],
      "correctAnswer": "b",
      "explanation": "The correct answer explains the concept tested in this question."
    },
    {
      "id": "q4",
      "question": "What is the CPU fetch-decode-execute cycle?",
      "type": "multiple-choice",
      "points": 10,
      "options": [
        {
          "id": "a",
          "text": "Load program, run program, close program"
        },
        {
          "id": "b",
          "text": "Get instruction, understand instruction, perform instruction"
        },
        {
          "id": "c",
          "text": "Read file, process file, save file"
        },
        {
          "id": "d",
          "text": "Input data, calculate data, output data"
        }
      ],
      "correctAnswer": "b",
      "explanation": "The correct answer explains the concept tested in this question."
    },
    {
      "id": "q5",
      "question": "What number system do computers use internally?",
      "type": "multiple-choice",
      "points": 10,
      "options": [
        {
          "id": "a",
          "text": "Decimal (base 10)"
        },
        {
          "id": "b",
          "text": "Binary (base 2)"
        },
        {
          "id": "c",
          "text": "Hexadecimal (base 16)"
        },
        {
          "id": "d",
          "text": "Octal (base 8)"
        }
      ],
      "correctAnswer": "b",
      "explanation": "The correct answer explains the concept tested in this question."
    },
    {
      "id": "q6",
      "question": "Why is Python generally slower than C?",
      "type": "multiple-choice",
      "points": 10,
      "options": [
        {
          "id": "a",
          "text": "Python has more features"
        },
        {
          "id": "b",
          "text": "Python is interpreted with runtime overhead"
        },
        {
          "id": "c",
          "text": "Python uses more memory"
        },
        {
          "id": "d",
          "text": "Python has worse syntax"
        }
      ],
      "correctAnswer": "b",
      "explanation": "The correct answer explains the concept tested in this question."
    },
    {
      "id": "q7",
      "question": "What happens with this code?\\n```python\\na = [1, 2, 3]\\nb = a\\nb.append(4)\\nprint(a)\\n```",
      "type": "multiple-choice",
      "points": 10,
      "options": [
        {
          "id": "a",
          "text": "[1, 2, 3]"
        },
        {
          "id": "b",
          "text": "[1, 2, 3, 4]"
        },
        {
          "id": "c",
          "text": "Error"
        },
        {
          "id": "d",
          "text": "[4]"
        }
      ],
      "correctAnswer": "b",
      "explanation": "The correct answer explains the concept tested in this question."
    },
    {
      "id": "q8",
      "question": "What is the main reason to understand computer architecture?",
      "type": "multiple-choice",
      "points": 10,
      "options": [
        {
          "id": "a",
          "text": "To build computers"
        },
        {
          "id": "b",
          "text": "To write more efficient code"
        },
        {
          "id": "c",
          "text": "To fix hardware issues"
        },
        {
          "id": "d",
          "text": "To design processors"
        }
      ],
      "correctAnswer": "b",
      "explanation": "The correct answer explains the concept tested in this question."
    },
    {
      "id": "q9",
      "question": "What keyword defines a function in Python?",
      "type": "multiple-choice",
      "points": 10,
      "options": [
        {
          "id": "a",
          "text": "function"
        },
        {
          "id": "b",
          "text": "def"
        },
        {
          "id": "c",
          "text": "func"
        },
        {
          "id": "d",
          "text": "define"
        }
      ],
      "correctAnswer": "b",
      "explanation": "The correct answer explains the concept tested in this question."
    },
    {
      "id": "q10",
      "question": "What is the output?\\n```python\\ndef greet(name):\\n    return f'Hello {name}'\\nprint(greet('Alice'))\\n```",
      "type": "multiple-choice",
      "points": 10,
      "options": [
        {
          "id": "a",
          "text": "Hello"
        },
        {
          "id": "b",
          "text": "Alice"
        },
        {
          "id": "c",
          "text": "Hello Alice"
        },
        {
          "id": "d",
          "text": "Error"
        }
      ],
      "correctAnswer": "c",
      "explanation": "The correct answer explains the concept tested in this question."
    },
    {
      "id": "q11",
      "question": "What does a function return if no return statement is specified?",
      "type": "multiple-choice",
      "points": 10,
      "options": [
        {
          "id": "a",
          "text": "0"
        },
        {
          "id": "b",
          "text": "None"
        },
        {
          "id": "c",
          "text": "Empty string"
        },
        {
          "id": "d",
          "text": "False"
        }
      ],
      "correctAnswer": "b",
      "explanation": "The correct answer explains the concept tested in this question."
    },
    {
      "id": "q12",
      "question": "What are function parameters?",
      "type": "multiple-choice",
      "points": 10,
      "options": [
        {
          "id": "a",
          "text": "Values returned by function"
        },
        {
          "id": "b",
          "text": "Variables in function definition"
        },
        {
          "id": "c",
          "text": "Function results"
        },
        {
          "id": "d",
          "text": "Function names"
        }
      ],
      "correctAnswer": "b",
      "explanation": "The correct answer explains the concept tested in this question."
    },
    {
      "id": "q13",
      "question": "What are function arguments?",
      "type": "multiple-choice",
      "points": 10,
      "options": [
        {
          "id": "a",
          "text": "Function definitions"
        },
        {
          "id": "b",
          "text": "Values passed when calling function"
        },
        {
          "id": "c",
          "text": "Function returns"
        },
        {
          "id": "d",
          "text": "Function names"
        }
      ],
      "correctAnswer": "b",
      "explanation": "The correct answer explains the concept tested in this question."
    },
    {
      "id": "q14",
      "question": "What is the output?\\n```python\\ndef add(a, b=10):\\n    return a + b\\nprint(add(5))\\n```",
      "type": "multiple-choice",
      "points": 10,
      "options": [
        {
          "id": "a",
          "text": "5"
        },
        {
          "id": "b",
          "text": "10"
        },
        {
          "id": "c",
          "text": "15"
        },
        {
          "id": "d",
          "text": "Error"
        }
      ],
      "correctAnswer": "c",
      "explanation": "The correct answer explains the concept tested in this question."
    },
    {
      "id": "q15",
      "question": "What are default parameters?",
      "type": "multiple-choice",
      "points": 10,
      "options": [
        {
          "id": "a",
          "text": "Required parameters"
        },
        {
          "id": "b",
          "text": "Parameters with preset values"
        },
        {
          "id": "c",
          "text": "First parameters"
        },
        {
          "id": "d",
          "text": "Last parameters"
        }
      ],
      "correctAnswer": "b",
      "explanation": "The correct answer explains the concept tested in this question."
    },
    {
      "id": "q16",
      "question": "Where must default parameters be placed?",
      "type": "multiple-choice",
      "points": 10,
      "options": [
        {
          "id": "a",
          "text": "At the beginning"
        },
        {
          "id": "b",
          "text": "In the middle"
        },
        {
          "id": "c",
          "text": "After non-default parameters"
        },
        {
          "id": "d",
          "text": "Anywhere"
        }
      ],
      "correctAnswer": "c",
      "explanation": "The correct answer explains the concept tested in this question."
    },
    {
      "id": "q17",
      "question": "What is the output?\\n```python\\ndef multiply(x, y):\\n    return x * y\\nresult = multiply(3, 4)\\nprint(result)\\n```",
      "type": "multiple-choice",
      "points": 10,
      "options": [
        {
          "id": "a",
          "text": "7"
        },
        {
          "id": "b",
          "text": "12"
        },
        {
          "id": "c",
          "text": "34"
        },
        {
          "id": "d",
          "text": "Error"
        }
      ],
      "correctAnswer": "b",
      "explanation": "The correct answer explains the concept tested in this question."
    },
    {
      "id": "q18",
      "question": "What does *args do in function definition?",
      "type": "multiple-choice",
      "points": 10,
      "options": [
        {
          "id": "a",
          "text": "Multiplies arguments"
        },
        {
          "id": "b",
          "text": "Accepts variable positional arguments"
        },
        {
          "id": "c",
          "text": "Requires all arguments"
        },
        {
          "id": "d",
          "text": "Returns multiple values"
        }
      ],
      "correctAnswer": "b",
      "explanation": "The correct answer explains the concept tested in this question."
    },
    {
      "id": "q19",
      "question": "What does **kwargs do in function definition?",
      "type": "multiple-choice",
      "points": 10,
      "options": [
        {
          "id": "a",
          "text": "Powers arguments"
        },
        {
          "id": "b",
          "text": "Accepts variable keyword arguments"
        },
        {
          "id": "c",
          "text": "Returns dictionary"
        },
        {
          "id": "d",
          "text": "Creates keywords"
        }
      ],
      "correctAnswer": "b",
      "explanation": "The correct answer explains the concept tested in this question."
    },
    {
      "id": "q20",
      "question": "What is the output?\\n```python\\ndef sum_all(*nums):\\n    return sum(nums)\\nprint(sum_all(1, 2, 3))\\n```",
      "type": "multiple-choice",
      "points": 10,
      "options": [
        {
          "id": "a",
          "text": "123"
        },
        {
          "id": "b",
          "text": "6"
        },
        {
          "id": "c",
          "text": "Error"
        },
        {
          "id": "d",
          "text": "None"
        }
      ],
      "correctAnswer": "b",
      "explanation": "The correct answer explains the concept tested in this question."
    },
    {
      "id": "q21",
      "question": "What is a lambda function?",
      "type": "multiple-choice",
      "points": 10,
      "options": [
        {
          "id": "a",
          "text": "Named function"
        },
        {
          "id": "b",
          "text": "Anonymous function"
        },
        {
          "id": "c",
          "text": "Built-in function"
        },
        {
          "id": "d",
          "text": "Imported function"
        }
      ],
      "correctAnswer": "b",
      "explanation": "The correct answer explains the concept tested in this question."
    },
    {
      "id": "q22",
      "question": "What is the output?\\n```python\\nsquare = lambda x: x ** 2\\nprint(square(4))\\n```",
      "type": "multiple-choice",
      "points": 10,
      "options": [
        {
          "id": "a",
          "text": "8"
        },
        {
          "id": "b",
          "text": "16"
        },
        {
          "id": "c",
          "text": "x ** 2"
        },
        {
          "id": "d",
          "text": "Error"
        }
      ],
      "correctAnswer": "b",
      "explanation": "The correct answer explains the concept tested in this question."
    },
    {
      "id": "q23",
      "question": "What is a docstring?",
      "type": "multiple-choice",
      "points": 10,
      "options": [
        {
          "id": "a",
          "text": "Function name"
        },
        {
          "id": "b",
          "text": "Function documentation string"
        },
        {
          "id": "c",
          "text": "Function parameter"
        },
        {
          "id": "d",
          "text": "Function return value"
        }
      ],
      "correctAnswer": "b",
      "explanation": "The correct answer explains the concept tested in this question."
    },
    {
      "id": "q24",
      "question": "How do you write a docstring?",
      "type": "multiple-choice",
      "points": 10,
      "options": [
        {
          "id": "a",
          "text": "# Comment"
        },
        {
          "id": "b",
          "text": "// Comment"
        },
        {
          "id": "c",
          "text": "Triple quotes at function start"
        },
        {
          "id": "d",
          "text": "Single quotes"
        }
      ],
      "correctAnswer": "c",
      "explanation": "The correct answer explains the concept tested in this question."
    },
    {
      "id": "q25",
      "question": "What is function scope?",
      "type": "multiple-choice",
      "points": 10,
      "options": [
        {
          "id": "a",
          "text": "Function size"
        },
        {
          "id": "b",
          "text": "Where variables are accessible"
        },
        {
          "id": "c",
          "text": "Function speed"
        },
        {
          "id": "d",
          "text": "Function type"
        }
      ],
      "correctAnswer": "b",
      "explanation": "The correct answer explains the concept tested in this question."
    },
    {
      "id": "q26",
      "question": "What is the output?\\n```python\\nx = 10\\ndef func():\\n    x = 20\\n    return x\\nprint(func())\\n```",
      "type": "multiple-choice",
      "points": 10,
      "options": [
        {
          "id": "a",
          "text": "10"
        },
        {
          "id": "b",
          "text": "20"
        },
        {
          "id": "c",
          "text": "30"
        },
        {
          "id": "d",
          "text": "Error"
        }
      ],
      "correctAnswer": "b",
      "explanation": "The correct answer explains the concept tested in this question."
    },
    {
      "id": "q27",
      "question": "What keyword modifies global variable in function?",
      "type": "multiple-choice",
      "points": 10,
      "options": [
        {
          "id": "a",
          "text": "global"
        },
        {
          "id": "b",
          "text": "public"
        },
        {
          "id": "c",
          "text": "extern"
        },
        {
          "id": "d",
          "text": "shared"
        }
      ],
      "correctAnswer": "a",
      "explanation": "The correct answer explains the concept tested in this question."
    },
    {
      "id": "q28",
      "question": "What is recursion?",
      "type": "multiple-choice",
      "points": 10,
      "options": [
        {
          "id": "a",
          "text": "Function calling itself"
        },
        {
          "id": "b",
          "text": "Multiple function calls"
        },
        {
          "id": "c",
          "text": "Function returning None"
        },
        {
          "id": "d",
          "text": "Function with no parameters"
        }
      ],
      "correctAnswer": "a",
      "explanation": "The correct answer explains the concept tested in this question."
    },
    {
      "id": "q29",
      "question": "What calculates factorial(3)?\\n```python\\ndef factorial(n):\\n    if n <= 1:\\n        return 1\\n    return n * factorial(n-1)\\n```",
      "type": "multiple-choice",
      "points": 10,
      "options": [
        {
          "id": "a",
          "text": "3"
        },
        {
          "id": "b",
          "text": "6"
        },
        {
          "id": "c",
          "text": "9"
        },
        {
          "id": "d",
          "text": "Error"
        }
      ],
      "correctAnswer": "b",
      "explanation": "The correct answer explains the concept tested in this question."
    },
    {
      "id": "q30",
      "question": "What is a higher-order function?",
      "type": "multiple-choice",
      "points": 10,
      "options": [
        {
          "id": "a",
          "text": "Complex function"
        },
        {
          "id": "b",
          "text": "Function that takes/returns functions"
        },
        {
          "id": "c",
          "text": "Fast function"
        },
        {
          "id": "d",
          "text": "Long function"
        }
      ],
      "correctAnswer": "b",
      "explanation": "The correct answer explains the concept tested in this question."
    },
    {
      "id": "q31",
      "question": "What does map() function do?",
      "type": "multiple-choice",
      "points": 10,
      "options": [
        {
          "id": "a",
          "text": "Creates maps"
        },
        {
          "id": "b",
          "text": "Applies function to all items"
        },
        {
          "id": "c",
          "text": "Filters items"
        },
        {
          "id": "d",
          "text": "Sorts items"
        }
      ],
      "correctAnswer": "b",
      "explanation": "The correct answer explains the concept tested in this question."
    },
    {
      "id": "q32",
      "question": "What does filter() function do?",
      "type": "multiple-choice",
      "points": 10,
      "options": [
        {
          "id": "a",
          "text": "Removes all items"
        },
        {
          "id": "b",
          "text": "Selects items based on condition"
        },
        {
          "id": "c",
          "text": "Sorts items"
        },
        {
          "id": "d",
          "text": "Counts items"
        }
      ],
      "correctAnswer": "b",
      "explanation": "The correct answer explains the concept tested in this question."
    },
    {
      "id": "q33",
      "question": "What is the output?\\n```python\\ndef func():\\n    return 1, 2, 3\\na, b, c = func()\\nprint(b)\\n```",
      "type": "multiple-choice",
      "points": 10,
      "options": [
        {
          "id": "a",
          "text": "1"
        },
        {
          "id": "b",
          "text": "2"
        },
        {
          "id": "c",
          "text": "3"
        },
        {
          "id": "d",
          "text": "(1, 2, 3)"
        }
      ],
      "correctAnswer": "b",
      "explanation": "The correct answer explains the concept tested in this question."
    },
    {
      "id": "q34",
      "question": "What are function annotations?",
      "type": "multiple-choice",
      "points": 10,
      "options": [
        {
          "id": "a",
          "text": "Function comments"
        },
        {
          "id": "b",
          "text": "Type hints for parameters and returns"
        },
        {
          "id": "c",
          "text": "Function names"
        },
        {
          "id": "d",
          "text": "Function calls"
        }
      ],
      "correctAnswer": "b",
      "explanation": "The correct answer explains the concept tested in this question."
    },
    {
      "id": "q35",
      "question": "What is a nested function?",
      "type": "multiple-choice",
      "points": 10,
      "options": [
        {
          "id": "a",
          "text": "Complex function"
        },
        {
          "id": "b",
          "text": "Function defined inside another function"
        },
        {
          "id": "c",
          "text": "Recursive function"
        },
        {
          "id": "d",
          "text": "Lambda function"
        }
      ],
      "correctAnswer": "b",
      "explanation": "The correct answer explains the concept tested in this question."
    },
    {
      "id": "q36",
      "question": "What is the output?\\n```python\\ndef outer():\\n    def inner():\\n        return 'Hi'\\n    return inner()\\nprint(outer())\\n```",
      "type": "multiple-choice",
      "points": 10,
      "options": [
        {
          "id": "a",
          "text": "inner"
        },
        {
          "id": "b",
          "text": "Hi"
        },
        {
          "id": "c",
          "text": "outer"
        },
        {
          "id": "d",
          "text": "Error"
        }
      ],
      "correctAnswer": "b",
      "explanation": "The correct answer explains the concept tested in this question."
    },
    {
      "id": "q37",
      "question": "What is a closure?",
      "type": "multiple-choice",
      "points": 10,
      "options": [
        {
          "id": "a",
          "text": "Closed function"
        },
        {
          "id": "b",
          "text": "Inner function remembering outer scope"
        },
        {
          "id": "c",
          "text": "Function with no return"
        },
        {
          "id": "d",
          "text": "Broken function"
        }
      ],
      "correctAnswer": "b",
      "explanation": "The correct answer explains the concept tested in this question."
    },
    {
      "id": "q38",
      "question": "What is the nonlocal keyword?",
      "type": "multiple-choice",
      "points": 10,
      "options": [
        {
          "id": "a",
          "text": "Creates local variable"
        },
        {
          "id": "b",
          "text": "Modifies enclosing scope variable"
        },
        {
          "id": "c",
          "text": "Creates global variable"
        },
        {
          "id": "d",
          "text": "Deletes variable"
        }
      ],
      "correctAnswer": "b",
      "explanation": "The correct answer explains the concept tested in this question."
    },
    {
      "id": "q39",
      "question": "What does reduce() function do?",
      "type": "multiple-choice",
      "points": 10,
      "options": [
        {
          "id": "a",
          "text": "Reduces size"
        },
        {
          "id": "b",
          "text": "Applies function cumulatively to reduce to single value"
        },
        {
          "id": "c",
          "text": "Filters items"
        },
        {
          "id": "d",
          "text": "Maps items"
        }
      ],
      "correctAnswer": "b",
      "explanation": "The correct answer explains the concept tested in this question."
    },
    {
      "id": "q40",
      "question": "Where is reduce() located?",
      "type": "multiple-choice",
      "points": 10,
      "options": [
        {
          "id": "a",
          "text": "Built-in"
        },
        {
          "id": "b",
          "text": "functools module"
        },
        {
          "id": "c",
          "text": "itertools module"
        },
        {
          "id": "d",
          "text": "collections module"
        }
      ],
      "correctAnswer": "b",
      "explanation": "The correct answer explains the concept tested in this question."
    },
    {
      "id": "q41",
      "question": "What is the output?\\n```python\\ndef func(x=[]):\\n    x.append(1)\\n    return x\\nprint(len(func()))\\nprint(len(func()))\\n```",
      "type": "multiple-choice",
      "points": 10,
      "options": [
        {
          "id": "a",
          "text": "1 1"
        },
        {
          "id": "b",
          "text": "1 2"
        },
        {
          "id": "c",
          "text": "2 2"
        },
        {
          "id": "d",
          "text": "Error"
        }
      ],
      "correctAnswer": "b",
      "explanation": "The correct answer explains the concept tested in this question."
    },
    {
      "id": "q42",
      "question": "Why is mutable default argument dangerous?",
      "type": "multiple-choice",
      "points": 10,
      "options": [
        {
          "id": "a",
          "text": "Causes syntax error"
        },
        {
          "id": "b",
          "text": "Shared between function calls"
        },
        {
          "id": "c",
          "text": "Slow performance"
        },
        {
          "id": "d",
          "text": "Uses too much memory"
        }
      ],
      "correctAnswer": "b",
      "explanation": "The correct answer explains the concept tested in this question."
    },
    {
      "id": "q43",
      "question": "What is function composition?",
      "type": "multiple-choice",
      "points": 10,
      "options": [
        {
          "id": "a",
          "text": "Writing functions"
        },
        {
          "id": "b",
          "text": "Combining functions together"
        },
        {
          "id": "c",
          "text": "Deleting functions"
        },
        {
          "id": "d",
          "text": "Importing functions"
        }
      ],
      "correctAnswer": "b",
      "explanation": "The correct answer explains the concept tested in this question."
    },
    {
      "id": "q44",
      "question": "What is a decorator?",
      "type": "multiple-choice",
      "points": 10,
      "options": [
        {
          "id": "a",
          "text": "Function that modifies another function"
        },
        {
          "id": "b",
          "text": "Function parameter"
        },
        {
          "id": "c",
          "text": "Function return value"
        },
        {
          "id": "d",
          "text": "Function name"
        }
      ],
      "correctAnswer": "a",
      "explanation": "The correct answer explains the concept tested in this question."
    },
    {
      "id": "q45",
      "question": "How do you apply a decorator?",
      "type": "multiple-choice",
      "points": 10,
      "options": [
        {
          "id": "a",
          "text": "#decorator"
        },
        {
          "id": "b",
          "text": "@decorator"
        },
        {
          "id": "c",
          "text": "decorator()"
        },
        {
          "id": "d",
          "text": "use decorator"
        }
      ],
      "correctAnswer": "b",
      "explanation": "The correct answer explains the concept tested in this question."
    },
    {
      "id": "q46",
      "question": "What is the purpose of return statement?",
      "type": "multiple-choice",
      "points": 10,
      "options": [
        {
          "id": "a",
          "text": "Start function"
        },
        {
          "id": "b",
          "text": "Send value back and exit function"
        },
        {
          "id": "c",
          "text": "Print value"
        },
        {
          "id": "d",
          "text": "Create variable"
        }
      ],
      "correctAnswer": "b",
      "explanation": "The correct answer explains the concept tested in this question."
    },
    {
      "id": "q47",
      "question": "Can a function return multiple values?",
      "type": "multiple-choice",
      "points": 10,
      "options": [
        {
          "id": "a",
          "text": "No, never"
        },
        {
          "id": "b",
          "text": "Yes, as a tuple"
        },
        {
          "id": "c",
          "text": "Only with special syntax"
        },
        {
          "id": "d",
          "text": "Only in Python 4"
        }
      ],
      "correctAnswer": "b",
      "explanation": "The correct answer explains the concept tested in this question."
    },
    {
      "id": "q48",
      "question": "What is function overloading?",
      "type": "multiple-choice",
      "points": 10,
      "options": [
        {
          "id": "a",
          "text": "Too many functions"
        },
        {
          "id": "b",
          "text": "Multiple functions with same name but different parameters"
        },
        {
          "id": "c",
          "text": "Recursive functions"
        },
        {
          "id": "d",
          "text": "Slow functions"
        }
      ],
      "correctAnswer": "b",
      "explanation": "The correct answer explains the concept tested in this question."
    },
    {
      "id": "q49",
      "question": "Does Python support function overloading directly?",
      "type": "multiple-choice",
      "points": 10,
      "options": [
        {
          "id": "a",
          "text": "Yes, fully supported"
        },
        {
          "id": "b",
          "text": "No, but can simulate with default args"
        },
        {
          "id": "c",
          "text": "Only in classes"
        },
        {
          "id": "d",
          "text": "Only with decorators"
        }
      ],
      "correctAnswer": "b",
      "explanation": "The correct answer explains the concept tested in this question."
    },
    {
      "id": "q50",
      "question": "What is the best practice for function length?",
      "type": "multiple-choice",
      "points": 10,
      "options": [
        {
          "id": "a",
          "text": "As long as possible"
        },
        {
          "id": "b",
          "text": "Keep functions focused and small"
        },
        {
          "id": "c",
          "text": "Exactly 100 lines"
        },
        {
          "id": "d",
          "text": "One function per file"
        }
      ],
      "correctAnswer": "b",
      "explanation": "The correct answer explains the concept tested in this question."
    }
  ],
  "description": "Test your understanding of this chapter",
  "timeLimit": 1800
}
